Workbook

Sheet Lisez-moi
B2: Agent BI de scoring automatique — Algorithmie détaillée par bonne pratique
B3: Veridash · Colas · Référentiel PR_Template_v3 · Document de conception v1.0
B5: Objet du classeur
B6: But | C6: Décrire, pour CHAQUE ligne du référentiel de bonnes pratiques, l'algorithme exact que l'agent exécute lorsqu'il parcourt le fichier Power BI (modèle sémantique, code Power Query M, rapport) afin de conclure OK / KO / PARTIEL / NON APPLICABLE, et avec quel niveau de confiance.
B8: Onglets
B9: Algorithmes_Regles | C9: Cœur du document : 1 ligne = 1 règle ou sous-règle, avec son algorithme, sa métrique, ses seuils, ses preuves et ses limites.
B10: Parametres | C10: Tous les seuils et listes administrables. Ce sont les seules valeurs à ajuster : le code ne contient aucune constante en dur.
B11: Synthese_Couverture | C11: Taux d'automatisation par catégorie et par criticité, calculé par formules sur l'onglet Algorithmes_Regles.
B12: Schema_MIR | C12: Structure de la représentation intermédiaire normalisée (Model Intermediate Representation) sur laquelle toutes les règles s'exécutent.
B13: Questions_Ouvertes | C13: Décisions à arbitrer avant développement, avec la valeur par défaut proposée.
B15: Classes d'automatisation
B16: A — Déterministe | C16: La conformité se lit directement dans les artefacts. Confiance ≥ 0,85. Le statut est pré-rempli automatiquement.
B17: B — Heuristique | C17: La conformité s'estime par un score et un seuil. Confiance 0,60 à 0,85. Le statut est pré-rempli mais marqué « à confirmer » et ne peut pas descendre en dessous de PARTIEL sans validation humaine.
B18: C — Humaine | C18: La conformité dépend d'un acte non observable (tester sur plusieurs navigateurs, profiler avec DAX Studio, juger un besoin futur). L'agent produit un pré-diagnostic chiffré et laisse le statut NON RENSEIGNÉ.
B20: Profils de seuils (colonne « Profil de seuils »)
B21: P1 — Strict (bloquant) | C21: OK si ρ = 1 ; KO sinon. Pas de statut PARTIEL. Réservé aux règles de criticité bloquante et déterministes.
B22: P2 — Standard | C22: OK si ρ ≥ 0,95 ; PARTIEL si 0,60 ≤ ρ < 0,95 ; KO si ρ < 0,60.
B23: P3 — Souple | C23: OK si ρ ≥ 0,85 ; PARTIEL si 0,50 ≤ ρ < 0,85 ; KO si ρ < 0,50.
B24: P4 — Seuils absolus | C24: Le verdict repose sur un compteur et non sur un ratio (ex. potentiel de mesures économisables).
B25: P5 — Humain | C25: Aucun statut n'est pré-rempli. L'agent dépose un pré-diagnostic, des preuves et une recommandation.
B27: Lecture de la colonne « Métrique de conformité »
B28: ρ (rhô) | C28: Taux de conformité de la règle, compris entre 0 et 1. C'est ce taux, confronté au profil de seuils, qui produit le statut. Le score global de la revue reste calculé par la formule existante de Veridash, inchangée : score = round((ok + 0,5 × partiel) / évalué × 100).
B30: Règle d'or
B31: Ne jamais écraser l'humain | C31: L'agent n'écrit un statut que sur un point de contrôle NON RENSEIGNÉ. Un statut saisi ou confirmé par un relecteur n'est jamais modifié par une nouvelle exécution : l'agent produit alors un écart signalé.
B32: Toujours joindre la preuve | C32: Un statut sans preuve exploitable (objet, emplacement, valeur observée) est refusé par le backend. Sans preuve, l'agent doit répondre INDÉTERMINÉ.

Sheet Algorithmes_Regles
A1: Algorithmie de l'agent BI — une ligne par bonne pratique
A2: ID | B2: Catégorie | C2: Niveau | D2: Rattachée à | E2: Libellé de la bonne pratique | F2: Criticité | G2: Classe | H2: Artefacts lus | I2: Objets analysés | J2: Précondition → Non applicable | K2: Algorithme détaillé exécuté par l'agent | L2: Métrique de conformité (ρ) | M2: Profil de seuils | N2: Confiance | O2: Preuves collectées (evidence) | P2: Limites / faux positifs connus | Q2: Remédiation proposée | R2: Coût algorithmique
A3: POWER QUERY
A4: PQ-01 | B4: Power Query | C4: Règle | E4: Poussez les transformations en amont, vers la source de données (dataflows / gold) lorsque cela est possible. | F4: Recommandé | G4: B | H4: DataMashup / Section1.m | I4: Requêtes M, étapes, connecteurs | J4: NA si aucune requête ne pointe vers une source relationnelle ou un dataflow (100 % fichiers plats locaux). | K4: 1. Parser Section1.m en AST M ; isoler chaque requête partagée (shared X = let ... in ...). 2. Identifier le connecteur racine : Sql.Database, DatabricksMultiCloud.Contents, Odbc.DataSource, PowerPlatform.Dataflows, SharePoint.Files, Excel.Workbook, Csv.Document, Web.Contents. 3. Marquer la requête 'pushdown-éligible' si connecteur ∈ {SQL, Databricks, Dataflow, ODBC}. 4. Pour chaque requête éligible, classer chaque étape aval avec la table de foldabilité : FOLDABLE = {Table.SelectRows, Table.SelectColumns, Table.RemoveColumns, Table.RenameColumns, Table.Group, Table.Distinct, Table.Sort, Table.NestedJoin(sur même source), Table.TransformColumnTypes} BARRIERE = {Table.Buffer, Table.AddIndexColumn, Table.Combine(sources hétérogènes), appel de fonction personnalisée, List.Generate, Table.AddColumn avec fonction non traduisible} 5. n_push = nb d'étapes FOLDABLE situées AVANT la 1re BARRIERE (= étapes qui auraient dû être en amont). 6. Si une requête native est présente (Value.NativeQuery ou option [Query="..."]) → n_push compté à 0 pour les étapes déjà couvertes par le SQL. 7. ρ = 1 − (Σ n_push / Σ étapes_éligibles). | L4: ρ = 1 − (étapes foldables restées côté PQ / étapes totales des requêtes éligibles) | M4: P3 (souple) | N4: 0,75 | O4: requete, etape, fonction_M, position, classement (FOLDABLE/BARRIERE) | P4: Le folding réel dépend du driver ; une étape théoriquement foldable peut ne pas l'être. Ne remplace pas la vérification 'Afficher la requête native'. | Q4: Déplacer les étapes listées vers la vue gold / le dataflow ou vers la requête SQL à la carte. | R4: O(S) sur le nb d'étapes — négligeable
A5: PQ-01a | B5: Power Query | C5: Sous-règle | D5: PQ-01 | E5: Utiliser le SQL à la carte lors d'une connexion à Databricks | F5: Recommandé | G5: A | H5: DataMashup / Section1.m | I5: Requêtes M avec connecteur Databricks | J5: NA si aucun connecteur Databricks détecté. | K5: 1. Collecter D = requêtes dont l'AST contient DatabricksMultiCloud.Contents, Databricks.Catalogs, ou Odbc.DataSource avec driver 'Simba Spark' / 'Databricks'. 2. Pour chaque d ∈ D, chercher dans les 2 premières étapes : Value.NativeQuery(source, texte, null, [EnableFolding=true]) OU un record d'options contenant la clé Query. 3. conforme(d) = 1 si trouvé, 0 sinon. 4. ρ = Σ conforme(d) / |D|. | L5: ρ = requêtes Databricks avec SQL natif / requêtes Databricks | M5: P2 (standard) | N5: 0,95 | O5: requete, connecteur, presence_native_query, extrait_sql (200 car.) | P5: Une navigation par catalogue/schéma/table sans SQL peut être volontaire pour les petites dimensions. | Q5: Remplacer la navigation par Value.NativeQuery avec EnableFolding=true. | R5: O(S)
A6: PQ-01b | B6: Power Query | C6: Sous-règle | D6: PQ-01 | E6: Inclure les étapes les plus simples dans le SQL à la carte (renommage, suppression de colonnes, colonnes ajoutées, jointure avec une autre table Databricks) | F6: Recommandé | G6: A | H6: DataMashup / Section1.m | I6: Étapes M postérieures à la requête native | J6: NA si aucune requête Databricks avec SQL natif (dépend de PQ-01a). | K6: 1. Pour chaque requête Databricks, se placer après l'étape Value.NativeQuery. 2. Compter les étapes SIMPLES = {Table.RenameColumns, Table.RemoveColumns, Table.SelectColumns, Table.AddColumn(expression sans fonction M complexe : opérateurs arithmétiques, concaténation, if/then/else à 1 niveau), Table.NestedJoin dont la table jointe provient du même hostname Databricks}. 3. n_simple = |étapes SIMPLES| ; n_total = |étapes après native query|. 4. ρ = 1 − n_simple / max(n_total, 1). | L6: ρ = 1 − étapes simples restées en PQ / étapes après le SQL natif | M6: P3 (souple) | N6: 0,85 | O6: requete, nom_etape, type_transformation, suggestion_SQL | P6: Une jointure vers une source non-Databricks ne peut pas être poussée : exclue du numérateur. | Q6: Intégrer les renommages / suppressions / jointures listés dans le SELECT. | R6: O(S)
A7: PQ-02 | B7: Power Query | C7: Règle | E7: Vérifiez les types de données et la précision des décimales. | F7: Recommandé | G7: A | H7: Modèle sémantique (TMDL/model.bim) + Section1.m | I7: Colonnes, étapes Table.TransformColumnTypes | J7: Jamais NA (tout modèle a des colonnes). | K7: 1. Indexer toutes les colonnes du modèle : (table, colonne, dataType, formatString, isHidden). 2. Détecter les colonnes NON TYPÉES : dataType = string alors que ≥ 95 % des valeurs échantillonnées sont numériques ou des dates (échantillon de 10 000 lignes si les données sont accessibles) ; sinon détecter l'absence d'étape Table.TransformColumnTypes dans la requête M correspondante → violation. 3. Détecter les types 'any' (Type.Any) laissés en M → violation systématique. 4. ρ = colonnes typées explicitement / colonnes totales. | L7: ρ = colonnes avec type explicite et cohérent / colonnes totales | M7: P2 (standard) | N7: 0,90 | O7: table, colonne, dataType, type_M, formatString | P7: Sans accès aux données (modèle DirectQuery), l'inférence de type se limite à l'analyse statique du M. | Q7: Ajouter/corriger l'étape Type modifié ; supprimer les colonnes de type Any. | R7: O(C) sur le nb de colonnes
A8: PQ-02a | B8: Power Query | C8: Sous-règle | D8: PQ-02 | E8: Mettre toutes les données décimales en fixed decimal, les nombres en format nombre entier et les pourcentages en pourcentage | F8: Recommandé | G8: A | H8: Modèle sémantique (TMDL/model.bim) + Section1.m | I8: Colonnes numériques | J8: NA si le modèle ne contient aucune colonne numérique. | K8: Pour chaque colonne numérique c : 1. DÉCIMAL : si dataType = double → attendu 'decimal' (Currency / Fixed Decimal, M = Currency.Type). Violation si dataType = double ET formatString ne contient pas '%'. 2. ENTIER : si dataType ∈ {double, decimal} ET (toutes les valeurs échantillonnées sont entières OU le nom matche ^(nb|nombre|qte|quantite|count|annee|mois|jour|id)) → attendu int64. Violation sinon. 3. POURCENTAGE : si nom matche (?i)(taux|pct|%|pourcent|ratio|part) OU formatString contient '%' → attendu formatString ∈ {0.00%, 0.0%, 0%} ET dataType = double. Violation si format numérique brut. 4. Croiser avec le M : Table.TransformColumnTypes doit déclarer Currency.Type / Int64.Type / Percentage.Type de façon cohérente ; incohérence M↔modèle = violation. 5. ρ = colonnes numériques conformes / colonnes numériques. | L8: ρ = colonnes numériques au bon type + bon format / colonnes numériques | M8: P2 (standard) | N8: 0,90 | O8: table, colonne, dataType_actuel, dataType_attendu, formatString, regle_declenchee | P8: La détection 'pourcentage' par le nom génère des faux positifs (ex. 'Ratio de conversion' déjà en décimal métier). Liste de mots-clés paramétrable. | Q8: Passer en Nombre décimal fixe / Nombre entier ; appliquer un format %. | R8: O(C)
A9: PQ-08 | B9: Power Query | C9: Règle | E9: Faites attention à la cardinalité des colonnes. Cherchez à réduire le nombre de valeurs uniques. | F9: Recommandé | G9: B | H9: Statistiques VertiPaq (DataModel) + modèle sémantique | I9: Colonnes des tables de faits | J9: NA si les statistiques de cardinalité sont indisponibles (Live connection sans XMLA). | K9: 1. Récupérer pour chaque colonne : distinctCount, tailleDictionnaire, tailleTotale (VertiPaq). 2. Calculer part_colonne = tailleTotale(c) / tailleTotale(modèle). 3. Marquer comme SUSPECTE toute colonne telle que : (a) dataType = dateTime ET distinctCount > 5 × nb_jours_couverts (⇒ composante horaire) ; (b) distinctCount / nbLignes > 0,80 ET colonne non clé de relation ; (c) part_colonne > 0,10 (colonne obèse) ; (d) dataType = double avec > 6 décimales significatives. 4. ρ = 1 − colonnes suspectes / colonnes de faits, pondéré par part_colonne. | L9: ρ pondéré = 1 − Σ part_colonne(suspectes) / Σ part_colonne(faits) | M9: P3 (souple) | N9: 0,70 | O9: table, colonne, distinctCount, taille_Mo, part_pct, motif | P9: Une forte cardinalité peut être fonctionnellement nécessaire (n° de facture). Sortie = recommandation, pas verdict dur. | Q9: Scinder date/heure, arrondir les décimaux, supprimer les identifiants techniques inutiles. | R9: O(C) — dépend de l'extraction des stats VertiPaq
A10: PQ-03 | B10: Power Query | C10: Règle | E10: Paramétrez les valeurs répétées et les sources dans Power Query | F10: Recommandé | G10: A | H10: DataMashup / Section1.m | I10: Littéraux, paramètres M | J10: NA si le modèle contient une seule requête sans littéral de connexion. | K10: 1. Extraire l'ensemble P des paramètres : requêtes M avec métadonnée IsParameterQuery=true. 2. Parcourir l'AST et collecter tous les littéraux texte L de longueur ≥ 4 apparaissant en position d'argument de connecteur (serveur, URL, chemin, catalogue, base, nom de fichier). 3. Regrouper L par valeur normalisée (casse/espaces) → multiset ; répété(l) = occurrences ≥ 2. 4. violations = |{l ∈ L : répété(l) ∧ l ∉ valeurs de P}|. 5. ρ = 1 − violations / (violations + |P utilisés|). | L10: ρ = paramètres utilisés / (paramètres + littéraux répétés en dur) | M10: P2 (standard) | N10: 0,90 | O10: valeur_litterale, nb_occurrences, requetes_concernees, parametre_suggere | P10: Un littéral répété non lié à une source (ex. libellé métier) est exclu par le filtre de position d'argument. | Q10: Créer un paramètre M et remplacer les occurrences. | R10: O(T) sur la taille du code M
A11: PQ-03a | B11: Power Query | C11: Sous-règle | D11: PQ-03 | E11: SharePoint : utiliser un paramètre pour chaque source Excel et chaque nom de fichier | F11: Recommandé | G11: A | H11: DataMashup / Section1.m | I11: SharePoint.Files, SharePoint.Contents, Excel.Workbook, Web.Contents | J11: NA si aucune source SharePoint / Excel. | K11: 1. S = requêtes contenant SharePoint.Files / SharePoint.Contents / Excel.Workbook(File.Contents(...)). 2. Pour chaque s ∈ S, extraire 2 arguments critiques : (i) URL du site, (ii) nom/chemin du fichier (argument de File.Contents ou prédicat Table.SelectRows sur [Name]). 3. checks(s) = 2 ; ok(s) = nb d'arguments qui sont une RÉFÉRENCE d'identifiant vers P (paramètre) et non un littéral texte. 4. ρ = Σ ok(s) / Σ checks(s). | L11: ρ = arguments SharePoint paramétrés / arguments SharePoint contrôlés (2 par source) | M11: P2 (standard) | N11: 0,95 | O11: requete, argument (site|fichier), valeur, est_parametre | P11: Une concaténation paramètre & littéral compte comme partiellement conforme (0,5) — paramétrable. | Q11: Créer les paramètres SiteSharePoint et NomFichier_x. | R11: O(S)
A12: PQ-03b | B12: Power Query | C12: Sous-règle | D12: PQ-03 | E12: Databricks : utiliser un paramètre pour le HTTP_Path, le Hostname et chaque catalogue utilisé (onecolasdata) | F12: Recommandé | G12: A | H12: DataMashup / Section1.m | I12: DatabricksMultiCloud.Contents / Odbc | J12: NA si aucun connecteur Databricks. | K12: 1. D = requêtes Databricks (cf. PQ-01a). 2. Pour chaque d, extraire 3 arguments : Hostname (arg 1), HTTP_Path (arg 2), Catalog (clé Catalog du record d'options ou 1er niveau de navigation). 3. ok(d) = nb d'arguments référençant un paramètre ; checks(d) = 3. 4. Contrôle additionnel : tous les d doivent référencer LE MÊME paramètre Hostname (sinon violation 'duplication de paramètre'). 5. ρ = Σ ok(d) / Σ checks(d). | L12: ρ = arguments Databricks paramétrés / (3 × nb de sources Databricks) | M12: P2 (standard) | N12: 0,95 | O12: requete, hostname, http_path, catalogue, est_parametre (×3) | P12: Un catalogue codé en dur mais unique dans tout le fichier reste une violation (règle explicite). | Q12: Créer les paramètres p_Hostname, p_HttpPath, p_Catalog. | R12: O(S)
A13: PQ-03c | B13: Power Query | C13: Sous-règle | D13: PQ-03 | E13: Serveur SQL : utiliser un paramètre pour le serveur et la base | F13: Recommandé | G13: A | H13: DataMashup / Section1.m | I13: Sql.Database / Sql.Databases | J13: NA si aucun connecteur SQL Server. | K13: 1. Q = requêtes contenant Sql.Database(server, database, options) ou Sql.Databases(server). 2. ok(q) = nb d'arguments parmi {server, database} qui sont une référence d'identifiant vers P. 3. checks(q) = 2 (ou 1 si Sql.Databases). 4. ρ = Σ ok / Σ checks. | L13: ρ = arguments SQL paramétrés / arguments SQL contrôlés | M13: P2 (standard) | N13: 0,95 | O13: requete, serveur, base, est_parametre | P13: Aucune notable. | Q13: Créer p_Serveur et p_BaseDeDonnees. | R13: O(S)
A14: PQ-04 | B14: Power Query | C14: Règle | E14: Désactivez le chargement des sources de données intermédiaires dans Power Query. | F14: Bloquant | G14: A | H14: DataMashup (Metadata) + modèle sémantique | I14: Requêtes M, tables du modèle | J14: NA si le graphe de dépendances ne comporte aucune requête intermédiaire. | K14: 1. Construire le graphe de dépendances G des requêtes : arc q1 → q2 si l'identifiant q1 apparaît dans le corps de q2. 2. INTERMÉDIAIRE(q) = deg_sortant(q) ≥ 1 (q est consommée par au moins une autre requête) ET q n'est pas un paramètre ET q n'est pas une fonction. 3. CHARGÉE(q) = il existe une table du modèle sémantique dont une partition a pour source la requête q (recoupement par nom exact, puis par empreinte du code M). 4. violation(q) = INTERMÉDIAIRE(q) ∧ CHARGÉE(q). Exception : q est aussi consommée directement par le rapport (référencée dans le Layout) → non violation. 5. ρ = 1 − |violations| / |intermédiaires|. | L14: ρ = intermédiaires non chargées / intermédiaires | M14: P1 (strict — bloquant) | N14: 0,95 | O14: requete, consommee_par[], table_modele_associee | P14: Une requête intermédiaire volontairement exposée (staging documenté) doit être déclarée en exception. | Q14: Décocher « Activer le chargement » sur les requêtes listées. | R14: O(V+E) sur le graphe de requêtes
A15: PQ-05 | B15: Power Query | C15: Règle | E15: En cas d'un direct query sur Databricks, s'assurer du pointage vers un endpoint dédié (consulter Data Ingénieur) | F15: Bloquant | G15: B | H15: Modèle sémantique (partitions) + Section1.m | I15: Partitions mode=directQuery, HTTP_Path | J15: NA si aucune partition en DirectQuery vers Databricks (cas majoritaire). | K15: 1. Filtrer les partitions dont mode ∈ {directQuery, dual} et dont l'expression source est Databricks. 2. Extraire la valeur résolue de HTTP_Path (si paramétrée, résoudre la valeur par défaut du paramètre). 3. Comparer à la liste blanche ENDPOINTS_DEDIES (référentiel administrable côté Veridash). 4. Si HTTP_Path ∈ liste blanche → OK. Si ∈ liste noire (endpoints mutualisés connus) → KO. Sinon → INDÉTERMINÉ : le statut n'est pas pré-rempli, un point de contrôle « à valider avec le Data Ingénieur » est généré avec la valeur observée. | L15: Booléen par partition DirectQuery ; ρ = partitions sur endpoint dédié / partitions DirectQuery | M15: P1 (strict) si liste blanche renseignée, sinon P5 (humain) | N15: 0,60 | O15: table, partition, mode, http_path_resolu, statut_liste | P15: Dépend entièrement de la liste blanche fournie par l'équipe Data. Sans elle, l'agent ne peut que constater. | Q15: Basculer vers l'endpoint SQL Warehouse dédié fourni par l'équipe Data. | R15: O(P) sur le nb de partitions
A16: PQ-06 | B16: Power Query | C16: Règle | E16: Vérifiez s'il est possible d'appliquer un filtre dynamique (via paramètre) pour restreindre la profondeur des données | F16: Bloquant | G16: B | H16: DataMashup / Section1.m + stats de volumétrie | I16: Table.SelectRows, paramètres date/nombre | J16: NA si aucune table > SEUIL_LIGNES (défaut 1 000 000) et modèle < 200 Mo. | K16: 1. Identifier les requêtes alimentant les tables volumineuses (nbLignes > SEUIL_LIGNES). 2. Pour chaque requête, rechercher un Table.SelectRows dont le prédicat référence un paramètre (identifiant ∈ P) portant sur une colonne de type date/datetime/entier. 3. Vérifier aussi la présence des paramètres normalisés RangeStart / RangeEnd. 4. conforme = présence d'au moins un filtre paramétré ; ρ = tables volumineuses filtrées / tables volumineuses. 5. Si absence, l'agent calcule la profondeur observée (min/max de la colonne date) pour objectiver l'écart. | L16: ρ = tables volumineuses avec filtre paramétré / tables volumineuses | M16: P2 (standard) | N16: 0,80 | O16: table, nb_lignes, colonne_date, min, max, filtre_detecte | P16: Le besoin fonctionnel peut exiger l'historique complet : à confirmer par le reviewer. | Q16: Ajouter un paramètre de profondeur et un Table.SelectRows en début de requête. | R16: O(S)
A17: PQ-07 | B17: Power Query | C17: Règle | E17: Renommez les étapes power query qui ne sont pas simples | F17: Recommandé | G17: A | H17: DataMashup / Section1.m | I17: Noms d'étapes M | J17: NA si toutes les requêtes ont ≤ 2 étapes. | K17: 1. Charger le dictionnaire multilingue des noms auto-générés : Source, Navigation, 'Type modifié'/'Changed Type', 'Lignes filtrées'/'Filtered Rows', 'Colonnes supprimées'/'Removed Columns', 'Personnalisé1'/'Custom1', 'Autres colonnes supprimées', etc., avec suffixe numérique optionnel (regex : ^(?:<libellé>)(?:\s?\d+)?$). 2. COMPLEXE(étape) = (longueur de l'expression > 120 caractères) OU (profondeur d'imbrication > 2) OU (fonction ∉ liste des 12 transformations triviales) OU (contient un if/each/let imbriqué). 3. violation = COMPLEXE(étape) ∧ nom auto-généré. 4. ρ = 1 − violations / |étapes complexes|. | L17: ρ = étapes complexes renommées / étapes complexes | M17: P2 (standard) | N17: 0,85 | O17: requete, nom_etape, longueur_expression, profondeur, nom_suggere | P17: Le dictionnaire doit couvrir la langue d'installation de Power BI Desktop (FR/EN a minima). | Q17: Renommer les étapes listées avec un libellé métier. | R17: O(S)
A18: MODÈLE
A19: MOD-01 | B19: Modèle | C19: Règle | E19: Assurez-vous que chaque rapport inclut une table de dates correctement marquée. | F19: Bloquant | G19: A | H19: Modèle sémantique (TMDL/model.bim) | I19: Tables, colonnes, relations | J19: NA si le modèle ne contient aucune colonne de type date/dateTime. | K19: Contrôle en 4 conditions cumulatives : C1 — Existence : ∃ table T avec dataCategory = 'Time' ET une colonne marquée isKey/'date column'. C2 — Type : la colonne marquée est de dataType date ou dateTime. C3 — Continuité : min(date) … max(date) sans jour manquant et couvrant des années civiles complètes (contrôle via distinctCount = (max−min)+1 en jours ; si les données ne sont pas lisibles, contrôle dégradé sur le code M/DAX de génération : CALENDAR, CALENDARAUTO, List.Dates). C4 — Usage : toute colonne date/dateTime des tables de faits participant à un visuel est reliée à T (relation active) ; sinon on liste les 'dates orphelines'. Verdict : OK si C1∧C2∧C3∧C4 ; PARTIEL si C1∧C2 mais C3 ou C4 en défaut ; KO si ¬C1. | L19: 4 conditions booléennes + ρ_C4 = colonnes date reliées / colonnes date utilisées | M19: P1 (strict — bloquant) | N19: 0,95 | O19: table_dates, colonne_marquee, min, max, jours_manquants, dates_orphelines[] | P19: Un modèle multi-calendriers (fiscal + civil) déclenche des faux positifs sur C4 : liste d'exception. | Q19: Marquer la table comme table de dates ; relier les colonnes date orphelines. | R19: O(C + R)
A20: MOD-02 | B20: Modèle | C20: Règle | E20: Désactiver la synthèse (summarization) automatique (∑) sur les colonnes des valeurs (désactiver les mesures implicites). | F20: Bloquant | G20: A | H20: Modèle sémantique (TMDL/model.bim) | I20: Colonnes numériques, propriété model.discourageImplicitMeasures | J20: Jamais NA. | K20: 1. N = colonnes de dataType ∈ {int64, double, decimal} hors colonnes de clé de relation et hors colonnes de la table de dates (année, mois, n° semaine — paramétrable). 2. violation(c) = summarizeBy ≠ 'none'. 3. Contrôle modèle : discourageImplicitMeasures = true → bonus, force OK si vrai ET aucune agrégation implicite dans le rapport (croisement avec DAX-01). 4. ρ = |{c ∈ N : summarizeBy = 'none'}| / |N|. | L20: ρ = colonnes numériques avec summarizeBy = none / colonnes numériques | M20: P1 (strict — bloquant, tolérance 100 %) | N20: 1,00 | O20: table, colonne, summarizeBy, isHidden | P20: Aucune — lecture directe d'une propriété du modèle. | Q20: Passer Résumé par défaut à « Ne pas résumer » sur les colonnes listées. | R20: O(C)
A21: MOD-03 | B21: Modèle | C21: Règle | E21: Masquer les champs techniques, numériques ou ceux non utilisés dans les rapports pour ne pas surcharger la liste des champs. | F21: Bloquant | G21: A | H21: Modèle sémantique + Report Layout | I21: Colonnes, tables, visuels | J21: Jamais NA. | K21: 1. Construire l'index d'usage U : pour chaque colonne, usage_visuel (référencée dans un projection/filtre/tri d'un visuel du Layout), usage_mesure (référencée dans une expression DAX), usage_relation, usage_hierarchie, usage_sortBy, usage_RLS. 2. TECHNIQUE(c) = nom matche ^(?i)(id|code|cle|key|sk|fk|guid|hash)_?|_(id|key|sk|fk)$ OU c participe à une relation côté clé. 3. DOIT_ETRE_MASQUEE(c) = TECHNIQUE(c) ∨ (aucun usage dans U ∧ c n'est pas un attribut d'analyse évident). 4. violation(c) = DOIT_ETRE_MASQUEE(c) ∧ isHidden = false. 5. ρ = 1 − violations / |{c : DOIT_ETRE_MASQUEE}|. | L21: ρ = champs à masquer effectivement masqués / champs à masquer | M21: P2 (standard) | N21: 0,85 | O21: table, colonne, isHidden, motif (technique|non_utilisee), usages[] | P21: Un champ non utilisé aujourd'hui peut être destiné à l'exploration libre : exception déclarable par table. | Q21: Masquer les colonnes listées. | R21: O(C + V) — un seul passage sur le Layout
A22: MOD-03a | B22: Modèle | C22: Sous-règle | D22: MOD-03 | E22: Si toutes les colonnes de la table de fait sont masquées, masquer la table directement | F22: Bloquant | G22: A | H22: Modèle sémantique | I22: Tables de faits | J22: NA si aucune table de fait identifiée. | K22: 1. Classer les tables (cf. MOD-05c) ; retenir F = tables de faits. 2. Pour chaque f ∈ F : toutes_masquees(f) = ∀ colonne c ∈ f, isHidden(c) = true. 3. violation(f) = toutes_masquees(f) ∧ isHidden(f) = false ∧ f ne porte aucune mesure visible. 4. ρ = 1 − violations / |{f : toutes_masquees(f)}|. | L22: ρ = tables entièrement masquées effectivement masquées / tables entièrement masquées | M22: P1 (strict) | N22: 0,95 | O22: table, nb_colonnes, nb_colonnes_masquees, isHidden_table, mesures_portees | P22: Si la table héberge des mesures visibles, elle doit rester visible : exclusion intégrée. | Q22: Masquer la table. | R22: O(T)
A23: MOD-04 | B23: Modèle | C23: Règle | E23: Évitez les relations bidirectionnelles et les relations many-to-many. Utilisez one-to-many et le modèle en etoile. | F23: Bloquant | G23: A | H23: Modèle sémantique (relations) | I23: Relations | J23: NA si le modèle ne contient aucune relation (modèle mono-table). | K23: 1. Charger le graphe de relations G(V=tables, E=relations) avec cardinalité et sens de filtrage. 2. Agréger MOD-04a (M2M) et MOD-04b (bidirectionnelles). 3. Contrôle étoile : détecter les chaînes dim→dim (flocon) par parcours ; profondeur > 1 = flocon. 4. Détecter les cycles (ambiguïté) par recherche de cycle dans le graphe non orienté des relations actives. 5. ρ = 1 − (n_m2m + n_bidir + n_cycles + 0,5 × n_flocons) / |E|. | L23: ρ pondéré sur l'ensemble des relations | M23: P1 (strict — bloquant) | N23: 0,95 | O23: table_source, table_cible, cardinalite, sens_filtrage, isActive, motif | P23: Le flocon est parfois légitime (hiérarchie produit normalisée) : pondération 0,5 et non 1. | Q23: Aplatir les dimensions, remplacer le M2M par une table de pont, désactiver le filtrage croisé. | R23: O(V+E)
A24: MOD-04a | B24: Modèle | C24: Sous-règle | D24: MOD-04 | E24: Eviter les relations plusieurs à plusieurs | F24: Bloquant | G24: A | H24: Modèle sémantique (relations) | I24: Relations | J24: NA si aucune relation. | K24: 1. n_m2m = |{r ∈ E : fromCardinality = many ∧ toCardinality = many}|. 2. Détecter aussi les M2M implicites : relation 1-N dont la colonne côté 1 n'est pas unique (distinctCount < nbLignes) → intégrité rompue assimilée M2M. 3. ρ = 1 − n_m2m / |E|. | L24: ρ = 1 − relations M2M / relations | M24: P1 (strict, tolérance 0) | N24: 1,00 | O24: relation, tables, cardinalite | P24: Aucune (lecture directe). | Q24: Introduire une table de pont et deux relations 1-N. | R24: O(E)
A25: MOD-04b | B25: Modèle | C25: Sous-règle | D25: MOD-04 | E25: Eviter les relations bidirectionnelles | F25: Bloquant | G25: A | H25: Modèle sémantique (relations) | I25: Relations | J25: NA si aucune relation. | K25: 1. n_bidir = |{r ∈ E : crossFilteringBehavior = 'bothDirections'}| (relations actives uniquement). 2. Exception admise : relation 1-1 vers une table de sécurité déclarée en liste blanche. 3. ρ = 1 − n_bidir / |E|. | L25: ρ = 1 − relations bidirectionnelles / relations | M25: P1 (strict, tolérance 0) | N25: 1,00 | O25: relation, tables, crossFilteringBehavior, isActive | P25: Aucune (lecture directe). | Q25: Passer en filtrage simple ; utiliser CROSSFILTER dans la mesure si nécessaire. | R25: O(E)
A26: MOD-05 | B26: Modèle | C26: Règle | E26: Nommer correctement les objets du modèles | F26: Recommandé | G26: B | H26: Modèle sémantique | I26: Tables, colonnes, mesures, hiérarchies | J26: Jamais NA. | K26: Agrégation pondérée de MOD-05a, MOD-05b, MOD-05c : ρ = (ρ_a + ρ_b + 2 × ρ_c) / 4 (le préfixage, objectivable, pèse double). | L26: ρ agrégé des trois sous-règles | M26: P3 (souple) | N26: 0,70 | O26: synthèse des trois sous-règles | P26: Règle composite : le détail doit toujours être présenté au reviewer. | Q26: Voir sous-règles. | R26: O(C)
A27: MOD-05a | B27: Modèle | C27: Sous-règle | D27: MOD-05 | E27: Assurez-vous que les noms soient concis, cohérents et logiques. | F27: Recommandé | G27: B | H27: Modèle sémantique | I27: Noms de tables, colonnes, mesures | J27: Jamais NA. | K27: Score de nommage sur 4 critères, par famille d'objets (tables / colonnes / mesures) : 1. CONCISION : longueur ≤ LONGUEUR_MAX (défaut 40) et nb de mots ≤ 6. 2. PROPRETÉ : pas de double espace, pas d'espace en début/fin, pas de caractère technique (_, ., #, [ ]) sauf préfixe D_/F_/T_ ; pas de suffixe résiduel (Column1, Colonne1, .1, _2, Sans titre). 3. COHÉRENCE DE CASSE : déterminer le style dominant par famille (Title Case / lowercase / UPPER / PascalCase) ; conformité = part des objets suivant le style dominant. 4. COHÉRENCE LEXICALE : un même concept doit porter le même mot (détection par regroupement des tokens quasi-identiques — distance de Levenshtein normalisée ≤ 0,2 mais graphie différente, ex. 'Client'/'Clients'/'CLIENT' sur des colonnes de tables différentes). ρ = moyenne des 4 taux de conformité. | L27: ρ = moyenne(concision, propreté, cohérence de casse, cohérence lexicale) | M27: P3 (souple) — jamais auto-rempli en KO, plafonné à PARTIEL | N27: 0,60 | O27: objet, nom, critere_en_defaut, style_dominant, suggestion | P27: Notion subjective : l'agent produit un diagnostic argumenté, la décision finale reste au reviewer. | Q27: Renommer les objets listés selon le style dominant du modèle. | R27: O(C log C) — regroupement lexical
A28: MOD-05b | B28: Modèle | C28: Sous-règle | D28: MOD-05 | E28: Ne pas mettre d'abréviation dans les noms de tables, colonnes et mesures | F28: Recommandé | G28: B | H28: Modèle sémantique | I28: Noms de tables, colonnes, mesures | J28: Jamais NA. | K28: 1. Tokeniser chaque nom (séparation espace, _, casse chameau). 2. Un token est ABRÉVIATION si : (a) présent dans le dictionnaire d'abréviations métier ABBR_LIST (Nb, Qte, Mt, Lib, Cd, Ref, Dt, Cli, Frs, Prd, Tot, Nom_Ct, Dsg…) — administrable, OU (b) longueur ≤ 4, absent des lexiques FR+EN, et absent de la liste blanche des sigles autorisés (CA, EBITDA, KPI, TVA, ETP, HT, TTC…), OU (c) supprime ≥ 2 voyelles internes par rapport à un mot du lexique à distance d'édition ≤ 3 (ex. 'Qte' → 'Quantite'). 3. ρ = 1 − |objets contenant ≥ 1 abréviation| / |objets|. | L28: ρ = 1 − objets avec abréviation / objets nommés | M28: P3 (souple) | N28: 0,70 | O28: objet, nom, token_abrege, mot_complet_suggere, source_detection | P28: Les sigles métier Colas doivent être injectés dans la liste blanche, sinon faux positifs massifs. | Q28: Développer les abréviations listées. | R28: O(C × L) — L = longueur moyenne des noms
A29: MOD-05c | B29: Modèle | C29: Sous-règle | D29: MOD-05 | E29: Mettre "D_" devant les tables de dimensions, "F_" devant les tables de fait et "T_" pour les tables techniques | F29: Recommandé | G29: A | H29: Modèle sémantique | I29: Tables | J29: NA si le modèle contient une seule table. | K29: 1. CLASSIFICATION STRUCTURELLE de chaque table t : • TECHNIQUE si : isHidden ∧ aucune relation, OU groupe de calcul, OU table de paramètre (annotation ParameterMetadata), OU table sans colonne visible ne portant que des mesures, OU nom ∈ {Mesures, Measures, Paramètres}. • FAIT si : t est côté « many » d'au moins une relation ET (t porte ≥ 1 colonne numérique additive OU nbLignes(t) > 10 × médiane des tables) ET t n'est côté « one » d'aucune relation. • DIMENSION si : t est côté « one » d'au moins une relation. • Conflit (côté one ET many) → table de flocon : classée DIMENSION, signalée. 2. Préfixe attendu = D_ / F_ / T_ selon la classe ; comparaison insensible à la casse. 3. ρ = tables correctement préfixées / tables classées. 4. Contrôle croisé : un préfixe présent mais contredit par la structure (ex. D_Ventes qui est un fait) est signalé en priorité haute. | L29: ρ = tables au bon préfixe / tables classables | M29: P2 (standard) | N29: 0,90 | O29: table, classe_deduite, prefixe_actuel, prefixe_attendu, justification_structurelle | P29: Un modèle mono-table ou en flocon profond rend la classification ambiguë : sortie 'INDÉTERMINÉ' par table. | Q29: Renommer les tables avec le préfixe correspondant à leur rôle. | R29: O(T + E)
A30: MOD-06 | B30: Modèle | C30: Règle | E30: Organiser les mesures | F30: Recommandé | G30: A | H30: Modèle sémantique | I30: Mesures, tables hôtes, dossiers d'affichage | J30: NA si le modèle ne contient aucune mesure. | K30: Agrégation : ρ = (ρ_MOD-06a + ρ_MOD-06b) / 2. | L30: ρ moyen des deux sous-règles | M30: P2 (standard) | N30: 0,90 | O30: synthèse des sous-règles | P30: — | Q30: Voir sous-règles. | R30: O(M)
A31: MOD-06a | B31: Modèle | C31: Sous-règle | D31: MOD-06 | E31: Regrouper les mesures dans des tables dédiées. | F31: Recommandé | G31: A | H31: Modèle sémantique | I31: Mesures, tables hôtes | J31: NA si aucune mesure. | K31: 1. TABLE_DE_MESURES(t) = t porte ≥ 1 mesure ET (t n'a aucune colonne visible OU t n'a aucune partition de données réelle — table calculée vide / table 'Mesures'). 2. violation(m) = table_hote(m) n'est pas une TABLE_DE_MESURES. 3. ρ = 1 − violations / |mesures|. 4. Contrôle secondaire : nb de tables de mesures ≤ NB_MAX_TABLES_MESURES (défaut 5) pour éviter l'éparpillement inverse. | L31: ρ = mesures hébergées dans une table dédiée / mesures | M31: P2 (standard) | N31: 0,90 | O31: mesure, table_hote, table_hote_est_dediee, nb_colonnes_visibles_hote | P31: Certaines organisations préfèrent la mesure dans sa table de faits : règle désactivable par profil. | Q31: Déplacer les mesures vers une table dédiée (Home table). | R31: O(M)
A32: MOD-06b | B32: Modèle | C32: Sous-règle | D32: MOD-06 | E32: Organiser les formules DAX et les champs dans des dossiers spécifiques. | F32: Recommandé | G32: A | H32: Modèle sémantique | I32: displayFolder des mesures et colonnes | J32: NA si le modèle contient < SEUIL_MESURES_DOSSIER (défaut 10) mesures. | K32: 1. ρ_mesures = |mesures avec displayFolder non vide| / |mesures|. 2. ρ_colonnes = |colonnes visibles avec displayFolder| / |colonnes visibles des tables ayant > 15 colonnes visibles| (les petites tables sont exclues). 3. Contrôle de structure : profondeur d'arborescence ≤ 3 ; pas de dossier contenant 1 seul élément (sur-découpage) ; pas de dossier contenant > 25 éléments (sous-découpage). 4. ρ = 0,7 × ρ_mesures + 0,3 × ρ_colonnes, minoré de 0,1 par anomalie de structure. | L32: ρ pondéré (mesures 70 % / colonnes 30 %) | M32: P2 (standard) | N32: 0,90 | O32: objet, displayFolder, profondeur, nb_elements_dossier | P32: Aucune notable. | Q32: Renseigner le dossier d'affichage des mesures et colonnes listées. | R32: O(M + C)
A33: MOD-07 | B33: Modèle | C33: Règle | E33: Ajouter des descriptions aux champs qui ne sont pas évidents dans le modèle. | F33: Recommandé | G33: B | H33: Modèle sémantique | I33: description des mesures, colonnes, tables | J33: Jamais NA. | K33: 1. NON_ÉVIDENT(objet) si au moins un critère : • c'est une mesure dont le code DAX dépasse SEUIL_TOKENS (défaut 30 jetons) ; • c'est une colonne calculée ; • le nom contient une abréviation détectée par MOD-05b ; • le nom est ambigu (token unique et générique : Montant, Valeur, Type, Statut, Code) ; • la colonne est un indicateur booléen / à codes (distinctCount ≤ 10 et dataType texte/entier). 2. conforme(objet) = longueur(description) ≥ LONGUEUR_MIN_DESC (défaut 20 caractères) ET la description n'est pas une simple recopie du nom (similarité < 0,9). 3. ρ = conformes / |objets non évidents|. | L33: ρ = objets non évidents documentés / objets non évidents | M33: P2 (standard) | N33: 0,75 | O33: objet, type, motif_non_evident, longueur_description, similarite_nom_description | P33: La détection « non évident » est heuristique ; le reviewer peut requalifier. | Q33: Renseigner la description des objets listés. | R33: O(M + C)
A34: MOD-07a | B34: Modèle | C34: Sous-règle | D34: MOD-07 | E34: Pour les datasets de build, toutes les descriptions fonctionelles longues doivent être remplies | F34: Recommandé | G34: A | H34: Modèle sémantique + contexte de la revue | I34: description de toutes les mesures et colonnes visibles | J34: NA si le type de livrable déclaré dans la revue ≠ « Build ». (Précondition contextuelle, pas technique.) | K34: 1. Lire le type de livrable depuis la revue Veridash (Power BI / App BI / Build). 2. Si ≠ Build → statut NA, aucune analyse. 3. Si Build : périmètre = toutes les mesures + toutes les colonnes visibles + toutes les tables visibles. 4. conforme = longueur(description) ≥ LONGUEUR_MIN_DESC_BUILD (défaut 60 caractères) ET contient ≥ 8 mots ET n'est pas une recopie du nom. 5. ρ = conformes / périmètre. Tolérance 0 en profil strict. | L34: ρ = objets visibles documentés (≥ 60 car.) / objets visibles | M34: P1 (strict) sur périmètre Build | N34: 0,95 | O34: objet, longueur_description, nb_mots | P34: Le seuil de 60 caractères est arbitraire : à calibrer sur 2-3 datasets de build validés. | Q34: Compléter les descriptions fonctionnelles. | R34: O(M + C)
A35: DAX
A36: DAX-01 | B36: DAX | C36: Règle | E36: Utiliser uniquement des mesures explicites pour plus de contrôle, de réutilisabilité et de clarté. | F36: Recommandé | G36: A | H36: Report Layout (JSON) + modèle sémantique | I36: Projections des visuels, colonnes agrégées | J36: NA si le rapport ne contient aucun visuel de données (rapport vide / template). | K36: 1. Parcourir Layout → sections → visualContainers → config.singleVisual.projections (et prototypeQuery / Query.Commands selon le format). 2. Pour chaque champ projeté, déterminer sa nature : référence de MESURE (queryRef pointant vers une mesure du modèle) vs référence de COLONNE avec agrégation (présence d'un nœud Aggregation : Sum/Avg/Min/Max/Count/CountNonNull). 3. n_implicites = nb de champs COLONNE+Agrégation ; n_total = nb de champs numériques projetés. 4. Croiser avec MOD-02 : si discourageImplicitMeasures = true, n_implicites doit être 0 par construction. 5. ρ = 1 − n_implicites / max(n_total, 1). | L36: ρ = 1 − agrégations implicites dans les visuels / champs numériques projetés | M36: P1 (strict, tolérance 0) | N36: 0,95 | O36: page, visuel, champ, table.colonne, fonction_agregation | P36: Un visuel Table/Matrice affichant une colonne texte n'est pas concerné : filtre sur champs numériques. | Q36: Créer les mesures explicites correspondantes et remplacer les champs dans les visuels. | R36: O(V × F) — un passage sur le Layout
A37: DAX-01a | B37: DAX | C37: Sous-règle | D37: DAX-01 | E37: Assurez-vous que chaque mesure DAX a un objectif précis et évitez de créer des mesures excessives ou redondantes qui compliquent inutilement le modèle. | F37: Recommandé | G37: B | H37: Modèle sémantique + Report Layout | I37: Mesures, graphe de dépendances | J37: NA si < 5 mesures. | K37: Deux détections indépendantes : A. MESURES NON UTILISÉES — construire le graphe de dépendances D : mesure → {mesures, colonnes} référencées (parsing des références [Nom] et 'Table'[Col]). Une mesure est ORPHELINE si elle n'est référencée par aucune autre mesure NI par aucun visuel/filtre/format conditionnel du Layout NI par une règle RLS. B. MESURES REDONDANTES — normaliser chaque expression (suppression des commentaires, des espaces superflus, mise en majuscules des fonctions, α-renommage des variables VAR en v1, v2, …), calculer h = SHA-256(expression normalisée). Doublon exact = même h. Quasi-doublon = similarité de Jaccard sur les empreintes de 5-grammes de jetons (winnowing / Rabin-Karp) ≥ 0,85. ρ = 1 − (|orphelines| + |doublons|) / |mesures|. | L37: ρ = 1 − (mesures orphelines + mesures redondantes) / mesures | M37: P3 (souple) | N37: 0,80 | O37: mesure, statut (orpheline|doublon), mesure_jumelle, similarite, empreinte | P37: Une mesure peut être utilisée par un rapport EXTERNE consommant le dataset partagé : si le modèle est publié, la détection d'orphelines doit être désactivée (paramètre DATASET_PARTAGE). | Q37: Supprimer les mesures orphelines ; fusionner les doublons. | R37: O(M × L) pour le hachage + O(M²) pire cas pour les quasi-doublons, ramené à O(M) par index inversé sur les empreintes (LSH)
A38: DAX-01b | B38: DAX | C38: Sous-règle | D38: DAX-01 | E38: Mettre dans des mesures à part les parties de code qui se répètent | F38: Recommandé | G38: B | H38: Modèle sémantique | I38: Sous-expressions DAX | J38: NA si < 5 mesures. | K38: 1. Tokeniser chaque expression DAX (jetons : fonctions, références, opérateurs, littéraux). 2. Extraire toutes les fenêtres de jetons de taille ≥ TAILLE_MIN_FRAGMENT (défaut 8) qui forment une expression syntaxiquement close (parenthèses équilibrées). 3. Empreinte de chaque fenêtre par winnowing (fenêtre glissante de 4, on conserve le hachage minimal) → index inversé empreinte → {mesures}. 4. FRAGMENT_À_FACTORISER = fenêtre présente dans ≥ NB_MIN_OCCURRENCES (défaut 3) mesures DISTINCTES, et qui ne correspond pas déjà à une référence de mesure existante. 5. ρ = 1 − |mesures impliquées dans ≥ 1 fragment| / |mesures|. | L38: ρ = 1 − mesures contenant du code dupliqué / mesures | M38: P3 (souple) | N38: 0,75 | O38: fragment (extrait), nb_occurrences, mesures_concernees[], nom_mesure_suggere | P38: Les motifs DAX idiomatiques courts (CALCULATE(...,ALL(...))) génèrent du bruit : TAILLE_MIN_FRAGMENT à calibrer. | Q38: Extraire les fragments listés dans des mesures intermédiaires réutilisables. | R38: O(Σ|jetons|) grâce au winnowing — linéaire
A39: DAX-02 | B39: DAX | C39: Règle | E39: Formater le code DAX dans le modèle pour en améliorer la lisibilité, (Revenir à la ligne et indenter les lignes) (Dax formatter) | F39: Recommandé | G39: B | H39: Modèle sémantique | I39: Expressions des mesures et colonnes calculées | J39: NA si aucune mesure ni colonne calculée. | K39: Deux stratégies combinées (la seconde départage) : A. HEURISTIQUE RAPIDE — une expression est MAL FORMATÉE si : • longueur > SEUIL_LONGUEUR (défaut 60 car.) ET nb de sauts de ligne = 0 ; • une ligne dépasse LARGEUR_MAX (défaut 120 car.) ; • indentation incohérente (pas d'augmentation d'indentation après une parenthèse ouvrante restée ouverte en fin de ligne) ; • mélange tabulations / espaces ; • absence d'espace autour des opérateurs binaires (=, <>, +, −, *, /) dans > 20 % des cas ; • mots-clés DAX non homogènes en casse (VAR/var, RETURN/return). B. DISTANCE AU FORMATAGE CANONIQUE — appliquer le pretty-printer DAX interne (règles DAX Formatter : une fonction par ligne, arguments indentés de 4, virgules en début de ligne) et calculer d = Levenshtein(actuel, formaté) / longueur(formaté) en ignorant les espaces multiples. Conforme si d ≤ SEUIL_DISTANCE (défaut 0,15). 3. conforme(m) = ¬A ∧ B ; ρ = conformes / |expressions|. | L39: ρ = expressions DAX formatées / expressions DAX | M39: P3 (souple) | N39: 0,80 | O39: mesure, longueur, nb_lignes, distance_formatage, criteres_en_defaut[] | P39: Le pretty-printer interne n'est pas bit-à-bit identique à daxformatter.com : d'où le seuil de tolérance 0,15 plutôt qu'une égalité stricte. | Q39: Passer les mesures listées dans DAX Formatter. | R39: O(Σ|expression|) — le pretty-printer n'est appliqué qu'aux expressions ayant échoué à l'heuristique A
A40: DAX-03 | B40: DAX | C40: Règle | E40: Utiliser des variables DAX pour améliorer la lisibilité du code. | F40: Recommandé | G40: A | H40: Modèle sémantique | I40: Expressions DAX complexes | J40: NA si aucune mesure ne franchit le seuil de complexité. | K40: 1. Calculer pour chaque expression un score de complexité : K = nb_jetons + 5 × profondeur_imbrication_max + 10 × nb_CALCULATE + 10 × nb_itérateurs (SUMX, AVERAGEX, FILTER, ADDCOLUMNS…). 2. COMPLEXE(m) = K ≥ SEUIL_COMPLEXITE (défaut 60). 3. conforme(m) = l'expression contient au moins un bloc VAR … RETURN. Contrôle de qualité additionnel : chaque VAR déclarée doit être utilisée (VAR morte = violation) ; une sous-expression identique répétée ≥ 2 fois dans la même mesure sans VAR = violation. 4. ρ = |{m complexes conformes}| / |{m complexes}|. | L40: ρ = mesures complexes utilisant VAR / mesures complexes | M40: P2 (standard) | N40: 0,90 | O40: mesure, score_complexite_K, presence_VAR, var_mortes[], sous_expressions_repetees[] | P40: Le seuil K est à calibrer ; une mesure longue mais linéaire (SWITCH à 20 branches) n'exige pas de VAR. | Q40: Introduire des variables VAR … RETURN dans les mesures listées. | R40: O(Σ|jetons|)
A41: DAX-04 | B41: DAX | C41: Règle | E41: Ajouter des commentaires utiles aux codes complexes (DAX, M). | F41: Recommandé | G41: B | H41: Modèle sémantique + Section1.m | I41: Expressions DAX et étapes M complexes | J41: NA si aucun code complexe (ni DAX ni M). | K41: 1. Périmètre = expressions DAX avec K ≥ SEUIL_COMPLEXITE (cf. DAX-03) ∪ requêtes M dont le nb d'étapes ≥ SEUIL_ETAPES (défaut 12) ou contenant une fonction personnalisée. 2. Extraire les commentaires : DAX → // et /* */ ; M → // et /* */. 3. UTILE(commentaire) = longueur ≥ 15 caractères ET ≥ 4 mots ET ratio de mots du lexique naturel > 0,5 (sinon c'est du code commenté, cf. DAX-06) ET ce n'est pas une simple recopie du nom de l'objet. 4. conforme(objet) = ≥ 1 commentaire UTILE, et couverture ≥ 1 commentaire par tranche de 40 lignes. 5. ρ = conformes / périmètre. | L41: ρ = objets complexes commentés utilement / objets complexes | M41: P3 (souple) | N41: 0,75 | O41: objet, langage (DAX|M), K ou nb_etapes, nb_commentaires, nb_commentaires_utiles | P41: La qualité sémantique d'un commentaire n'est pas évaluable statiquement — seule sa présence et sa vraisemblance le sont. Option : évaluation LLM en second passage (cf. §IA du document d'algorithmie). | Q41: Commenter les blocs complexes listés. | R41: O(Σ|code|)
A42: DAX-05 | B42: DAX | C42: Règle | E42: Envisager d'utiliser des groupes de calcul (calculation groups) pour réduire le nombre de mesures | F42: Optionnel | G42: A | H42: Modèle sémantique | I42: Groupes de calcul, familles de mesures | J42: NA si < SEUIL_MESURES_CG (défaut 15) mesures dans le modèle. | K42: 1. Détecter l'existence de groupes de calcul : table avec calculationGroup / calculationItems non vide. 2. Détecter les FAMILLES DE VARIANTES : regrouper les mesures par racine de nom après suppression des suffixes/préfixes du dictionnaire TIME_INTEL = {YTD, MTD, QTD, LY, PY, N-1, N-2, YoY, Var, Var %, Cumul, Glissant, R12, Rolling}. Une famille = même racine, ≥ NB_MIN_VARIANTES (défaut 3) variantes distinctes. 3. potentiel = Σ (|famille| − 1) sur toutes les familles = nb de mesures économisables. 4. Verdict : OK si groupes de calcul présents OU potentiel < NB_MIN_ECONOMIE (défaut 8). PARTIEL si potentiel ∈ [8, 20[. KO si potentiel ≥ 20 et aucun groupe de calcul. | L42: potentiel = nb de mesures supprimables par mise en place de groupes de calcul | M42: P4 (par seuils absolus) | N42: 0,85 | O42: familles[] {racine, variantes[], taille}, potentiel, groupes_calcul_existants[] | P42: Les groupes de calcul sont incompatibles avec certains usages (mesures implicites, Excel Analyser dans) : la règle est classée Optionnel et ne bloque jamais. | Q42: Créer un groupe de calcul Time Intelligence couvrant les familles listées. | R42: O(M log M) — regroupement par racine
A43: DAX-06 | B43: DAX | C43: Règle | E43: Supprimer les parties de codes inutiles mis en commentaire | F43: Recommandé | G43: A | H43: Modèle sémantique + Section1.m | I43: Commentaires DAX et M | J43: NA si aucun commentaire dans tout le code. | K43: 1. Extraire tous les blocs de commentaires (DAX et M). 2. CODE_COMMENTÉ(bloc) = score ≥ 2 sur les indices suivants : +1 si le bloc contient une fonction DAX/M connue suivie de '(' ; +1 si le bloc contient une référence 'Table'[Colonne] ou [Mesure] ; +1 si le ratio de caractères de ponctuation de code (=,(),[],") > 0,12 ; +1 si le bloc est syntaxiquement parsable comme une expression DAX/M ; −2 si le ratio de mots du lexique naturel (FR/EN) > 0,6. 3. violations = |blocs CODE_COMMENTÉ|. 4. ρ = 1 − violations / |blocs de commentaires| ; verdict KO dès violations ≥ 1 en profil strict. | L43: nb de blocs de code mort en commentaire (cible : 0) | M43: P1 (strict, tolérance 0) | N43: 0,85 | O43: objet, extrait_commentaire (150 car.), score_indices, lignes | P43: Un exemple d'usage volontairement commenté dans une mesure de documentation est un faux positif (rare). Le reviewer peut requalifier. | Q43: Supprimer les blocs de code commenté listés. | R43: O(Σ|code|)
A44: GÉNÉRAL
A45: GEN-01 | B45: Général | C45: Règle | E45: Éliminez les champs et données inutiles. | F45: Recommandé | G45: A | H45: Modèle sémantique + Report Layout + Section1.m | I45: Colonnes, tables, mesures, requêtes | J45: Jamais NA. | K45: 1. Réutiliser l'index d'usage U construit pour MOD-03 (visuels, mesures, relations, hiérarchies, sortByColumn, RLS, paramètres de champ, format conditionnel, info-bulles, signets). 2. INUTILE(colonne) = aucun usage dans U. INUTILE(table) = toutes ses colonnes inutiles ET aucune mesure hébergée ET aucune relation. INUTILE(requête M) = non chargée ET non référencée par une autre requête. 3. Pondération par le poids VertiPaq : poids(c) = tailleTotale(c) / tailleTotale(modèle) (si stats disponibles), sinon poids uniforme. 4. ρ = 1 − Σ poids(objets inutiles) / Σ poids(objets). 5. L'agent produit le gain estimé en Mo. | L45: ρ pondéré par la taille + gain estimé (Mo) | M45: P2 (standard) | N45: 0,85 | O45: objet, type, usages_trouves (0), taille_Mo, gain_estime | P45: Identique à DAX-01a : un dataset partagé peut être consommé par des rapports externes. Paramètre DATASET_PARTAGE = true → la règle passe en pré-diagnostic sans verdict. | Q45: Supprimer les colonnes/tables/requêtes listées. | R45: O(C + V + E) — index d'usage mutualisé avec MOD-03 et DAX-01a
A46: GEN-02 | B46: Général | C46: Règle | E46: Désactivez l'option Auto Date/Time : Fichier > Options et paramètres > Options > Chargement des données - Time Intelligence (Date/heure automatique pour les nouveaux fichiers). | F46: Bloquant | G46: A | H46: Modèle sémantique (annotations + tables) | I46: Annotation __PBI_TimeIntelligenceEnabled, tables LocalDateTable_* | J46: Jamais NA. | K46: Contrôle doublement redondant (les deux doivent être vrais) : C1 — l'annotation modèle __PBI_TimeIntelligenceEnabled vaut 0 (ou est absente). C2 — aucune table du modèle ne matche ^(LocalDateTable_|DateTableTemplate_)[0-9a-f-]{36}$ et aucune hiérarchie automatique 'Variations'/'Date Hierarchy' générée. Verdict : OK si C1 ∧ C2 ; KO sinon. L'agent compte les tables auto générées et estime le poids récupérable (chaque table auto pèse typiquement 1 à 5 Mo). | L46: Booléen ; nb de tables de date automatiques (cible 0) | M46: P1 (strict, tolérance 0) | N46: 1,00 | O46: annotation, valeur, tables_auto[], colonnes_declencheuses[], poids_estime_Mo | P46: Aucune — détection totalement déterministe. | Q46: Décocher Date/heure automatique puis republier ; supprimer les hiérarchies de dates automatiques. | R46: O(T)
A47: GEN-03 | B47: Général | C47: Règle | E47: Limitez les logiques métier complexes dans la couche de rapport afin de maintenir la simplicité, la facilité de maintenance et les performances du modèle. | F47: Recommandé | G47: B | H47: Report Layout + modèle sémantique | I47: Mesures de rapport, filtres de visuel, format conditionnel, calculs visuels | J47: NA si le rapport est en connexion live vers un dataset partagé et ne contient aucune mesure de rapport. | K47: Score de fuite de logique métier L = somme pondérée : • 3 × nb de mesures définies au niveau du rapport (report-level measures) ; • 3 × nb de calculs visuels (visual calculations) ; • 2 × nb de règles de format conditionnel avec expression FieldValue/DAX ; • 1 × nb de filtres de visuel de type Advanced avec ≥ 2 conditions ; • 2 × nb de champs 'Custom' / paramètres de champ créés dans le rapport ; • 1 × nb de visuels contenant une expression de tri personnalisée. Normalisation : L_n = L / max(nb_visuels, 1). Verdict : OK si L_n ≤ 0,5 ; PARTIEL si 0,5 < L_n ≤ 1,5 ; KO si L_n > 1,5. | L47: L_n = score de logique métier au niveau rapport / nb de visuels | M47: P4 (par seuils absolus) | N47: 0,65 | O47: page, visuel, type_de_logique, extrait, poids | P47: Le format conditionnel est un usage légitime : pondération faible. Règle plafonnée à PARTIEL en auto-remplissage, jamais KO sans confirmation humaine. | Q47: Remonter les mesures de rapport dans le modèle sémantique. | R47: O(V)
A48: GEN-04 | B48: Général | C48: Règle | E48: Choisissez le bon niveau d'agrégation pour répondre aux besoins actuels et futurs des rapports, en évitant la granularité maximale. | F48: Recommandé | G48: C | H48: Statistiques VertiPaq + Report Layout | I48: Tables de faits, granularité observée vs granularité utilisée | J48: NA si les statistiques de cardinalité sont indisponibles. | K48: PRÉ-DIAGNOSTIC (pas de verdict automatique) : 1. Pour chaque table de fait f : identifier les colonnes de grain (clés de relation + colonne date). 2. Calculer la granularité STOCKÉE = nbLignes(f). 3. Calculer la granularité UTILISÉE = produit des cardinalités des seuls niveaux effectivement projetés dans les visuels (issus de l'index d'usage U), en prenant pour chaque dimension le niveau le plus fin réellement affiché. 4. ratio_surqualite = granularité STOCKÉE / granularité UTILISÉE. 5. Si ratio > 10 → l'agent signale un potentiel d'agrégation avec gain estimé, mais laisse le statut NON RENSEIGNÉ : la décision dépend des besoins futurs, non observables. 6. Contrôle secondaire objectivable : présence d'une colonne dateTime avec composante horaire alors qu'aucun visuel n'affiche l'heure → violation objectivable, celle-ci peut être pré-remplie. | L48: ratio_surqualite par table de fait (indicatif) + violation horaire (objectivable) | M48: P5 (humain) — pré-diagnostic uniquement | N48: 0,40 | O48: table, nb_lignes, grain_stocke[], grain_utilise[], ratio, gain_estime_Mo | P48: « Besoins futurs » n'est pas observable. Toute automatisation d'un verdict ici serait arbitraire : l'agent documente, le reviewer tranche. | Q48: Envisager une table d'agrégation ou une montée en grain à la source. | R48: O(T + V)
A49: GEN-05 | B49: Général | C49: Règle | E49: Vérifier l'intégrité référentielle des relations. | F49: Bloquant | G49: A | H49: Modèle sémantique + données (VertiPaq) | I49: Relations, colonnes de clé | J49: NA si aucune relation, ou si les données ne sont pas lisibles (DirectQuery pur) → INDÉTERMINÉ. | K49: Pour chaque relation r (côté 1 = dimension D.k, côté N = fait F.fk) : C1 — UNICITÉ : distinctCount(D.k) = nbLignes(D) (sinon la relation 1-N est invalide). C2 — INCLUSION : |valeurs distinctes de F.fk \ valeurs distinctes de D.k| = 0. Implémentation : construire un filtre de Bloom (ou un hachage de l'ensemble) sur D.k, puis un seul balayage de F.fk → O(n+m) au lieu d'une jointure. C3 — NULLS : nb de valeurs vides/nulles dans F.fk (ligne blanche générée). C4 — TYPES : dataType(D.k) = dataType(F.fk). C5 — DRAPEAU : relyOnReferentialIntegrity = true doit être posé UNIQUEMENT si C1∧C2∧C3 sont satisfaits (sinon incohérence dangereuse en DirectQuery). ρ = relations satisfaisant C1..C5 / |relations|. Si les données ne sont pas accessibles, seuls C1 (via stats), C4 et C5 sont évalués → confiance 0,6 et statut plafonné à PARTIEL. | L49: ρ = relations à intégrité vérifiée / relations | M49: P1 (strict — bloquant) | N49: 0,90 (données lisibles) / 0,60 (sinon) | O49: relation, unicite_ok, nb_cles_orphelines, exemples_cles_orphelines[5], nb_nulls, types | P49: Coût mémoire du filtre de Bloom sur les très grosses dimensions : paramétrer un taux de faux positifs à 1e-6 puis vérifier exactement les candidats remontés. | Q49: Corriger les clés orphelines à la source ; ajouter une ligne 'Inconnu' dans la dimension. | R49: O(n+m) par relation avec filtre de Bloom
A50: MISE EN PAGE & DESIGN
A51: DSG-01 | B51: Mise en page & Design | C51: Règle | E51: Bien respecter le template CDS si utilisé | F51: Recommandé | G51: B | H51: Report Layout + thème (StaticResources) + fichier de référence CDS | I51: Thème, palette, polices, dimensions de page, éléments de gabarit | J51: NA si l'utilisateur déclare que le template CDS n'est pas utilisé (question posée au lancement de l'agent). | K51: 1. Charger le THÈME DE RÉFÉRENCE CDS (JSON déposé une fois pour toutes dans Veridash). 2. Extraire du rapport : nom du thème, dataColors[], background, foreground, tableAccent, fontFamily par classe de texte, taille de page (width/height), displayOption. 3. Comparer attribut par attribut : • palette : similarité = |couleurs communes| / |couleurs de référence| (comparaison en espace colorimétrique CIELAB, ΔE ≤ 2 = identique) ; • polices : égalité stricte des familles ; • dimensions : égalité stricte (ex. 1280×720) ; • éléments de gabarit : présence des formes/images nommées dans la référence (bandeau, logo, pied de page) sur chaque page — comparaison par nom et par position (tolérance ± 5 px). 4. ρ = attributs conformes / attributs contrôlés (pondération : palette 30 %, polices 20 %, dimensions 20 %, éléments 30 %). | L51: ρ pondéré de conformité au gabarit CDS | M51: P2 (standard) | N51: 0,85 (si thème de référence fourni) / 0,00 sinon → NA | O51: attribut, valeur_rapport, valeur_reference, ecart (ΔE ou px) | P51: Sans le fichier de thème CDS de référence chargé dans Veridash, la règle est inévaluable. | Q51: Appliquer le thème CDS et repositionner les éléments de gabarit. | R51: O(P × E) — P pages, E éléments de gabarit
A52: DSG-02 | B52: Mise en page & Design | C52: Règle | E52: Visualiser et tester le rapport sur différents écrans, navigateurs et contextes. | F52: Recommandé | G52: C | H52: Report Layout | I52: Mise en page mobile, débordements, options d'affichage | J52: Jamais NA — mais le verdict final reste humain. | K52: PRÉ-DIAGNOSTIC objectivable (l'acte de test lui-même n'est pas observable) : I1 — MISE EN PAGE MOBILE : existe-t-il une disposition mobile définie pour chaque page (layouts avec id = 1 / section mobileState non vide) ? taux = pages avec mobile / pages. I2 — DÉBORDEMENT : pour chaque visuel, x + width ≤ largeur_page et y + height ≤ hauteur_page ; compter les visuels hors canevas. I3 — CHEVAUCHEMENT : détecter les paires de visuels dont les rectangles se recouvrent de > 10 % (algorithme de balayage / sweep line en O(V log V)) — hors visuels appartenant à des signets exclusifs. I4 — OPTION D'AFFICHAGE : displayOption = FitToPage recommandé (vs ActualSize). I5 — TAILLE MINIMALE : visuels de moins de 80×60 px (illisibles sur petit écran). L'agent renseigne un pré-diagnostic ; si I2 ou I3 remontent des anomalies, le statut proposé est KO (objectivable). Sinon le statut reste NON RENSEIGNÉ avec la mention « test manuel requis ». | L52: I1..I5 ; verdict auto uniquement si débordement ou chevauchement détecté | M52: P5 (humain) sauf anomalie objectivable → P1 | N52: 0,50 | O52: page, visuel, x, y, w, h, anomalie, mobile_defini | P52: Le test navigateur/contexte utilisateur est par nature manuel. | Q52: Définir les dispositions mobiles ; corriger les débordements et chevauchements. | R52: O(V log V) pour le balayage géométrique
A53: DSG-03 | B53: Mise en page & Design | C53: Règle | E53: Organiser et regrouper les visuels et les signets dans le volet Sélection pour une meilleure structure. | F53: Recommandé | G53: A | H53: Report Layout | I53: Groupes de visuels, noms de visuels, signets | J53: NA si le rapport a < 5 visuels et 0 signet. | K53: 1. GROUPEMENT : taux_groupes = visuels appartenant à un groupe (parentGroupName renseigné) / visuels, calculé uniquement sur les pages ayant > SEUIL_VISUELS (défaut 8) visuels. 2. NOMMAGE : un visuel est mal nommé si son titre/nom d'affichage matche le motif par défaut ^(?i)(visual|visuel|graphique|group|groupe)\s?\d*$ ou est vide. taux_nommage = 1 − mal_nommés / visuels. 3. SIGNETS : un signet est mal nommé si ^(?i)(signet|bookmark)\s?\d+$. Les signets doivent être rangés dans des groupes (bookmark groups) dès qu'il y en a > 5. taux_signets. 4. ρ = 0,4 × taux_groupes + 0,3 × taux_nommage + 0,3 × taux_signets (les composantes non applicables sont retirées et les poids renormalisés). | L53: ρ pondéré (groupement / nommage / signets) | M53: P3 (souple) | N53: 0,85 | O53: page, visuel_ou_signet, nom, groupe, anomalie | P53: Un rapport simple (3 visuels/page) n'a pas besoin de groupes : seuil d'activation par page. | Q53: Grouper et renommer les éléments dans le volet Sélection. | R53: O(V + B)
A54: DSG-04 | B54: Mise en page & Design | C54: Règle | E54: Eliminer les interactions inutiles entre les visuels pour améliorer la clarté. | F54: Recommandé | G54: B | H54: Report Layout (section.config.relationships) | I54: Matrice d'interactions entre visuels | J54: NA si toutes les pages ont ≤ 2 visuels. | K54: 1. Pour chaque page, construire la matrice d'interactions I[s][c] ∈ {none, filter, highlight} (valeur par défaut = filter/highlight si non explicitée dans relationships). 2. Calculer la LIGNÉE de chaque visuel : ensemble des tables du modèle atteintes par ses champs, étendu par le graphe de relations (fermeture transitive limitée aux relations actives et au sens de filtrage effectif). 3. INTERACTION_INUTILE(s,c) = I[s][c] ≠ none ET lignée(s) ∩ lignée_filtrable(c) = ∅ (le visuel source ne peut structurellement pas filtrer la cible) — détection objectivable. 4. INTERACTION_SUSPECTE(s,c) = I[s][c] ≠ none ET c est un visuel de type carte/KPI de contexte global (heuristique paramétrable). 5. ρ = 1 − (inutiles + 0,5 × suspectes) / |paires actives|. 6. Contrôle inverse : si AUCUNE interaction n'a été personnalisée sur une page de > 8 visuels, signaler « interactions jamais revues » (indice de non-conformité, pas preuve). | L54: ρ = 1 − interactions inutiles pondérées / paires d'interactions actives | M54: P3 (souple) | N54: 0,70 | O54: page, visuel_source, visuel_cible, type_interaction, lignee_source[], lignee_cible[] | P54: Une interaction 'inutile' au sens lignée peut être voulue via un signet ou une mesure transverse : la détection par lignée est conservatrice (ne remonte que les cas structurellement impossibles). | Q54: Désactiver les interactions listées via Format > Modifier les interactions. | R54: O(P × V²) borné en pratique (V ≤ 30 par page) + O(E) pour la fermeture transitive, mise en cache
A55: DSG-05 | B55: Mise en page & Design | C55: Règle | E55: Configurer et tester toutes les interactions et filtres (cross-filtrage, slicers, etc) | F55: Recommandé | G55: A | H55: Report Layout + modèle sémantique | I55: Slicers, filtres de page/rapport/visuel, matrice d'interactions | J55: NA si aucun filtre ni slicer. | K55: Contrôles objectivables (les seuls automatisables) : C1 — FILTRES ORPHELINS : tout champ référencé par un filtre ou un slicer doit exister dans le modèle (comparaison des queryRef avec l'index des objets). Un filtre pointant vers un champ supprimé = KO dur. C2 — FILTRES VIDES : filtres de type Advanced/Basic sans condition renseignée. C3 — SLICERS SANS CIBLE : slicer dont le champ appartient à une table sans aucun chemin de filtrage vers les tables des visuels de la page (calcul de lignée, cf. DSG-04) → le slicer ne filtre rien. C4 — INTERACTIONS PERSONNALISÉES : au moins une entrée explicite dans relationships sur les pages de > 5 visuels (indice que les interactions ont été revues). C5 — FILTRES DE RAPPORT masqués/verrouillés cohérents. ρ = contrôles passés / contrôles applicables. C1 et C3 déclenchent un KO même isolément. | L55: ρ sur C1..C5, avec C1/C3 bloquants | M55: P2 (standard) avec KO dur sur C1/C3 | N55: 0,85 | O55: page, element, type, champ_reference, existe_dans_modele, chemin_de_filtrage | P55: Le « test » réel (cliquer et vérifier le comportement) reste humain ; l'agent garantit seulement l'absence d'incohérence structurelle. | Q55: Corriger les filtres orphelins ; supprimer les slicers sans effet. | R55: O(V + F)
A56: DSG-06 | B56: Mise en page & Design | C56: Règle | E56: Synchroniser les slicers là où c'est nécessaire | F56: Recommandé | G56: A | H56: Report Layout (syncGroups) | I56: Slicers, groupes de synchronisation | J56: NA si le rapport a une seule page ou aucun slicer. | K56: 1. Indexer les slicers par (champ du modèle) → {pages}. 2. CANDIDAT_SYNC(champ) = le champ est utilisé comme slicer sur ≥ 2 pages. 3. Lire les groupes de synchronisation (config du slicer : syncGroup.groupName, fieldChanges, filterChanges). 4. violation(champ) = CANDIDAT_SYNC(champ) ET les slicers correspondants n'appartiennent pas tous au même groupe de synchronisation avec filterChanges = true. 5. ρ = 1 − violations / |candidats|. 6. Contrôle inverse : slicer synchronisé mais dont le champ n'existe pas sur la page cible → signalement (synchronisation orpheline). | L56: ρ = champs multi-pages synchronisés / champs multi-pages | M56: P2 (standard) | N56: 0,90 | O56: champ, pages[], groupe_sync, filterChanges, visible_sur | P56: La non-synchronisation peut être un choix fonctionnel (comparaison de deux périodes sur deux pages) : exception déclarable. | Q56: Créer un groupe de synchronisation pour les champs listés. | R56: O(V)
A57: DSG-07 | B57: Mise en page & Design | C57: Règle | E57: Éliminer les visuels inutiles ou redondants. | F57: Recommandé | G57: A | H57: Report Layout | I57: Visuels | J57: NA si < 3 visuels au total. | K57: 1. Calculer pour chaque visuel une SIGNATURE = SHA-256 de (type_visuel, ensemble trié des queryRef projetés, ensemble trié des filtres de visuel, ordre de tri). 2. REDONDANT = deux visuels de la même page partageant la même signature (hors visuels appartenant à des signets mutuellement exclusifs — détection via l'appartenance à des états de signets disjoints). 3. VIDE = visuel sans aucun champ projeté (hors formes, images, zones de texte, boutons). 4. INVISIBLE_MORT = visuel avec isHidden = true qui n'est activé par aucun signet. 5. QUASI-REDONDANT = même type + Jaccard(champs) ≥ 0,8 → signalé sans verdict. 6. ρ = 1 − (redondants + vides + invisibles_morts) / |visuels de données|. | L57: ρ = 1 − visuels redondants/vides/morts / visuels de données | M57: P2 (standard) | N57: 0,85 | O57: page, visuel, type, signature, jumeau, motif | P57: Deux visuels identiques peuvent servir à un mécanisme de bascule (bookmark toggle) : l'exclusion par signets couvre le cas principal. | Q57: Supprimer les visuels listés. | R57: O(V) avec table de hachage
A58: DSG-08 | B58: Mise en page & Design | C58: Règle | E58: Désactiver les en-têtes des visuels si non nécessaires. | F58: Recommandé | G58: B | H58: Report Layout (objects.visualHeader) | I58: Propriété d'en-tête des visuels | J58: NA si aucun visuel de données. | K58: 1. Pour chaque visuel, lire objects.visualHeader[].properties.show (défaut = affiché). 2. NÉCESSAIRE(v) = au moins une action d'en-tête a du sens : drill-down/drill-up activé (hiérarchie projetée), focus mode utile (visuel dense : > 20 points de données ou table/matrice), info-bulle personnalisée, filtre de visuel actif à rendre visible, export de données autorisé. 3. violation(v) = ¬NÉCESSAIRE(v) ∧ show = true. 4. ρ = 1 − violations / |{v : ¬NÉCESSAIRE(v)}|. 5. Contrôle inverse signalé : NÉCESSAIRE(v) ∧ show = false (fonctionnalité rendue inaccessible). | L58: ρ = en-têtes masqués là où inutiles / visuels sans besoin d'en-tête | M58: P3 (souple) | N58: 0,65 | O58: page, visuel, show, criteres_necessite[] | P58: « Nécessaire » est une appréciation UX : l'agent applique une heuristique documentée, plafonnée à PARTIEL en auto-remplissage. | Q58: Masquer les en-têtes des visuels listés. | R58: O(V)
A59: DSG-09 | B59: Mise en page & Design | C59: Règle | E59: Ajouter le bandeau de notification | F59: Recommandé | G59: A | H59: Report Layout + gabarit CDS de référence | I59: Zone de texte / forme / image du bandeau | J59: NA si le gabarit de référence CDS n'est pas déclaré (dépend de DSG-01). | K59: 1. Charger la DÉFINITION DU BANDEAU depuis le gabarit de référence : nom d'objet attendu (ex. 'Bandeau_Notification'), type (textbox/shape/image), zone de position attendue (bande supérieure : y ≤ 60 px, largeur ≥ 0,9 × largeur de page). 2. Pour chaque page (hors pages masquées et pages d'info-bulle), rechercher un objet satisfaisant : • nom matche le motif attendu (insensible à la casse/accents), OU • type + géométrie dans la zone attendue + contenu textuel matche le motif MOTIF_BANDEAU (regex administrable, ex. (?i)(donn[ée]es? (mises? à jour|actualis)|derni[èe]re actualisation|notification)). 3. ρ = pages avec bandeau conforme / pages éligibles. 4. Contrôle additionnel : le bandeau est-il au même emplacement sur toutes les pages (écart ≤ 5 px) ? | L59: ρ = pages portant le bandeau / pages éligibles | M59: P2 (standard) | N59: 0,85 (si motif fourni) | O59: page, objet_trouve, nom, type, x, y, w, h, texte (100 car.) | P59: Nécessite que la définition exacte du bandeau Colas soit chargée dans Veridash une fois pour toutes. | Q59: Ajouter le bandeau de notification sur les pages listées. | R59: O(P × E)
A60: DSG-10 | B60: Mise en page & Design | C60: Règle | E60: Définir la landing page sur la bonne page ("landingpage" visible dans le report .json) | F60: Recommandé | G60: A | H60: Report Layout / report.json | I60: Propriété de page d'accueil, ordre des pages | J60: NA si le rapport ne contient qu'une seule page. | K60: 1. Rechercher dans le JSON du rapport la clé de page d'accueil (selon le format : 'landingPage' dans la configuration du rapport, ou pageBinding/type = 'LandingPage', ou activeSectionIndex). 2. C1 — la propriété est présente et non vide. 3. C2 — elle référence une page EXISTANTE (le nom/identifiant se résout dans sections[]). 4. C3 — la page référencée est VISIBLE (visibility ≠ HiddenInViewMode) et n'est ni une page d'info-bulle (type Tooltip) ni une page de type drillthrough. 5. C4 — cohérence avec l'ordinal : la page d'accueil est celle d'ordinal 0, ou l'écart est explicable. Verdict : OK si C1∧C2∧C3 ; PARTIEL si C1∧C2 mais ¬C4 ; KO si ¬C1 ou ¬C2 ou ¬C3. | L60: 4 conditions booléennes | M60: P1 (strict) | N60: 0,90 | O60: cle_trouvee, valeur, page_resolue, page_visible, ordinal, type_page | P60: La clé exacte varie selon la version du format (PBIX Layout vs PBIR report.json) : l'extracteur doit couvrir les deux, et la règle passe en INDÉTERMINÉ si aucune clé connue n'est trouvée. | Q60: Définir la page d'accueil sur la page d'entrée du rapport. | R60: O(P)
A61: MODÈLE DE DONNÉES CONSÉQUENT (> 1GO)
A62: BIG-00 | B62: Modèle de données conséquent (> 1Go) | C62: Précondition | E62: [Précondition de catégorie] Le modèle dépasse-t-il 1 Go ? | F62: — | G62: A | H62: Taille du fichier + statistiques VertiPaq | I62: Modèle | J62: — | K62: 1. taille_modele = max(taille VertiPaq totale décompressée en mémoire, taille du fichier .pbix hors ressources statiques). 2. Si taille_modele < SEUIL_GROS_MODELE (défaut 1 Go) → TOUTES les règles BIG-01..BIG-06 sont positionnées à NON APPLICABLE en un seul geste, avec la taille observée en justification. 3. Zone grise : si 0,8 Go ≤ taille < 1 Go, les règles sont évaluées mais le statut proposé est consultatif (non bloquant) — le modèle est proche du seuil. 4. Sinon → les 6 règles sont évaluées normalement. | L62: taille_modele (Mo) vs seuil | M62: Aiguillage (pas de statut propre) | N62: 0,95 | O62: taille_fichier_Mo, taille_vertipaq_Mo, seuil, decision | P62: La taille en mémoire diffère de la taille du fichier compressé (facteur 2 à 5) : c'est la taille VertiPaq qui fait foi quand elle est disponible. | Q62: — | R62: O(1)
A63: BIG-01 | B63: Modèle de données conséquent (> 1Go) | C63: Règle | E63: Exploitez le query folding lorsque possible pour maximiser l'efficacité des transformations. | F63: Recommandé | G63: B | H63: DataMashup / Section1.m | I63: Chaînes d'étapes M | J63: NA si BIG-00 = faux, ou si aucune source foldable. | K63: 1. Pour chaque requête sur source foldable (SQL, Databricks, ODBC, OData, dataflow) : 2. Parcourir les étapes dans l'ordre et déterminer l'INDICE DE RUPTURE = position de la première étape classée BARRIERE (cf. table de foldabilité de PQ-01, enrichie : Table.Buffer, Table.AddIndexColumn, fonctions personnalisées, Table.FromList, accès à Web.Contents, Table.Combine hétérogène, opérations sur des colonnes de type record/list). 3. n_perdues = nb d'étapes FOLDABLE situées APRÈS l'indice de rupture (= folding perdu inutilement). 4. folding_ratio(q) = indice_de_rupture / nb_etapes(q). 5. ρ = moyenne pondérée des folding_ratio, pondérée par la volumétrie de la table produite. 6. L'agent produit la liste ordonnée des étapes à déplacer avant la rupture (gain immédiat). | L63: ρ = moyenne pondérée du taux d'étapes situées avant la rupture de folding | M63: P3 (souple) | N63: 0,70 | O63: requete, indice_rupture, etape_rupture, etapes_perdues[], volumetrie_table | P63: L'analyse statique ne remplace pas « Afficher la requête native » : certaines étapes théoriquement foldables ne le sont pas selon le driver. Confiance volontairement modérée. | Q63: Remonter les étapes foldables avant l'étape de rupture identifiée. | R63: O(S)
A64: BIG-02 | B64: Modèle de données conséquent (> 1Go) | C64: Règle | E64: Évitez les fusions (merge) et les ajouts (append) - réservez les étapes « coûteuses » qui lisent l'ensemble des données pour la fin. | F64: Recommandé | G64: A | H64: DataMashup / Section1.m | I64: Table.NestedJoin, Table.Join, Table.Combine, Table.Group, Table.Sort, Table.Distinct | J64: NA si BIG-00 = faux, ou si aucune étape coûteuse. | K64: 1. COÛTEUSES = {Table.NestedJoin, Table.Join, Table.Combine, Table.Group, Table.Sort, Table.Distinct, Table.Pivot, Table.Unpivot, Table.Buffer}. 2. RÉDUCTRICES = {Table.SelectRows, Table.SelectColumns, Table.RemoveColumns, Table.FirstN}. 3. Pour chaque requête q, soit pos(e) la position normalisée d'une étape (0 = début, 1 = fin). 4. violation type A : ∃ étape coûteuse c et étape réductrice r avec pos(c) < pos(r) (on filtre APRÈS avoir joint → lecture inutile de données). 5. violation type B : nb d'étapes coûteuses > NB_MAX_COUTEUSES (défaut 3) dans une même requête. 6. score(q) = position moyenne des étapes coûteuses (idéalement proche de 1). 7. ρ = moyenne des score(q) pénalisée de 0,15 par violation de type A. | L64: ρ = position moyenne normalisée des étapes coûteuses, pénalisée par les inversions | M64: P3 (souple) | N64: 0,85 | O64: requete, etape_couteuse, position, etapes_reductrices_apres[], type_violation | P64: Une jointure précoce peut être nécessaire pour construire le prédicat de filtrage : cas signalé mais pondéré. | Q64: Déplacer les filtres et suppressions de colonnes avant les fusions/regroupements. | R64: O(S)
A65: BIG-03 | B65: Modèle de données conséquent (> 1Go) | C65: Règle | E65: Appliquez un filtre précoce et paramétré pour limiter les données lors de l'étape de développement. | F65: Recommandé | G65: A | H65: DataMashup / Section1.m | I65: Table.SelectRows, paramètres | J65: NA si BIG-00 = faux. | K65: 1. Pour chaque requête alimentant une table volumineuse : 2. Rechercher un Table.SelectRows dont le prédicat référence un identifiant ∈ P (paramètre). 3. PRÉCOCE = la position de ce filtre ≤ POSITION_MAX_FILTRE (défaut : dans les 3 premières étapes après Source, ou position normalisée ≤ 0,25). 4. conforme(q) = filtre paramétré présent ∧ précoce. 5. Contrôle additionnel : le paramètre de développement doit être documenté (description non vide) et sa valeur par défaut doit être une valeur de production sûre. 6. ρ = conformes / requêtes volumineuses. | L65: ρ = requêtes volumineuses avec filtre paramétré précoce / requêtes volumineuses | M65: P2 (standard) | N65: 0,90 | O65: requete, filtre_trouve, position, parametre_utilise, valeur_par_defaut | P65: Recouvrement partiel avec PQ-06 : les deux règles restent distinctes (PQ-06 = profondeur fonctionnelle, BIG-03 = confort de développement). Les preuves sont mutualisées. | Q65: Ajouter un paramètre de profondeur et un filtre en tête de requête. | R65: O(S)
A66: BIG-04 | B66: Modèle de données conséquent (> 1Go) | C66: Règle | E66: Configurez l'actualisation incremental si vous devez actualiser uniquement les données modifiées ou récentes. | F66: Recommandé | G66: A | H66: Modèle sémantique (refreshPolicy) + paramètres M | I66: Politique d'actualisation incrémentielle, RangeStart/RangeEnd | J66: NA si BIG-00 = faux, ou si aucune table de fait avec colonne date. | K66: Contrôle en 5 conditions par table de fait volumineuse f : C1 — f possède une refreshPolicy (policyType = basic) ; C2 — les paramètres RangeStart et RangeEnd existent, de type dateTime ; C3 — la requête M de f contient un Table.SelectRows utilisant RangeStart (≥) et RangeEnd (<) avec les bons opérateurs (inclusif/exclusif) — une erreur d'opérateur provoque des doublons ou des trous : contrôle explicite ; C4 — les fenêtres incrementalPeriods/rollingWindow sont cohérentes (rollingWindow ≥ incrementalWindow) ; C5 — le folding est préservé jusqu'au filtre RangeStart/RangeEnd (sinon la partition est évaluée en mémoire → contre-productif ; croisement avec BIG-01). ρ = Σ conditions satisfaites / (5 × nb de tables volumineuses éligibles). | L66: ρ sur C1..C5 par table de fait volumineuse | M66: P2 (standard) | N66: 0,90 | O66: table, refreshPolicy, incrementalWindow, rollingWindow, operateurs_filtre, folding_preserve | P66: L'actualisation incrémentielle peut être configurée côté service et non dans le fichier : si le modèle est publié, croiser avec l'API REST Power BI (extension possible). | Q66: Configurer l'actualisation incrémentielle avec RangeStart/RangeEnd. | R66: O(T + S)
A67: BIG-05 | B67: Modèle de données conséquent (> 1Go) | C67: Règle | E67: Évaluer les performances du DAX avec DAX Studio. | F67: Recommandé | G67: C | H67: Modèle sémantique (analyse statique) | I67: Mesures, anti-motifs DAX | J67: NA si BIG-00 = faux. | K67: PRÉ-DIAGNOSTIC (l'exécution d'un profilage n'est pas observable dans les artefacts) : 1. Détecter les ANTI-MOTIFS de performance par analyse de l'arbre syntaxique : • FILTER(Table_entière, …) au lieu de FILTER(VALUES(col), …) ou d'un prédicat CALCULATE ; • itérateurs imbriqués (SUMX dans SUMX) ; • DISTINCTCOUNT sur une colonne à très forte cardinalité ; • EARLIER (remplaçable par VAR) ; • conversions implicites dans des comparaisons (colonne texte comparée à un nombre) ; • ALL() sur une table de faits entière ; • fonctions de time intelligence appliquées sans table de dates marquée ; • IF imbriqués > 5 niveaux (préférer SWITCH). 2. score_risque(m) = Σ poids des anti-motifs détectés. 3. L'agent produit le TOP 10 des mesures à profiler, classé par score_risque × nb d'usages dans les visuels. 4. Statut : NON RENSEIGNÉ (l'acte de profilage reste humain) SAUF si score_risque = 0 sur l'ensemble du modèle → proposition OK avec mention « aucun anti-motif détecté ». | L67: score_risque global + top 10 des mesures à profiler | M67: P5 (humain) — pré-diagnostic | N67: 0,50 | O67: mesure, anti_motifs[], score_risque, nb_usages, extrait_code | P67: Ne mesure pas les temps d'exécution réels ; ne remplace pas DAX Studio. Fournit la liste de travail, pas le verdict. | Q67: Profiler les mesures listées dans DAX Studio et corriger les anti-motifs. | R67: O(Σ|jetons|)
A68: BIG-06 | B68: Modèle de données conséquent (> 1Go) | C68: Règle | E68: Vérifier si des boutons « Appliquer » sont nécessaires pour les Slicers et le volet de filtres. | F68: Recommandé | G68: A | H68: Report Layout (paramètres du rapport et des slicers) | I68: Bouton Appliquer du volet de filtres, sélection unique/multiple des slicers | J68: NA si BIG-00 = faux et si aucune partition en DirectQuery. | K68: 1. NÉCESSITÉ : le bouton Appliquer est requis si (modèle > seuil) OU (≥ 1 partition en DirectQuery/Dual) OU (≥ SEUIL_SLICERS (défaut 4) slicers sur une même page). 2. DÉTECTION : lire dans la configuration du rapport le drapeau d'application différée des filtres (bouton Appliquer du volet de filtres) et, pour chaque slicer, la présence d'un bouton Appliquer/mode de sélection différée. 3. conforme(page) = ¬nécessité(page) ∨ (bouton présent). 4. ρ = pages conformes / pages. 5. Si le drapeau n'est pas trouvable dans le format lu → INDÉTERMINÉ (pas de pré-remplissage), avec un rappel du contexte (taille du modèle, mode de stockage). | L68: ρ = pages conformes / pages nécessitant un bouton Appliquer | M68: P2 (standard) | N68: 0,75 | O68: page, nb_slicers, mode_stockage, bouton_appliquer_detecte, necessite | P68: La clé de configuration du bouton Appliquer dépend de la version du format de rapport : à valider sur un échantillon réel avant mise en production de la règle. | Q68: Activer le bouton Appliquer sur le volet de filtres et les slicers concernés. | R68: O(P + V)

Sheet Parametres
A1: Paramètres administrables de l'agent
A2: Les cellules en jaune sont les seules valeurs à modifier. Aucune de ces constantes n'est écrite en dur dans le code de l'agent.
A4: Domaine | B4: Paramètre | C4: Valeur | D4: Rôle | E4: Format attendu
A5: Extraction | B5: FORMAT_ENTREE_PRIORITAIRE | C5: pbip | D5: Format lu en priorité : pbip (dossier projet, TMDL/JSON) ou pbix. | E5: pbip | pbix | xmla
A6: Extraction | B6: TAILLE_MAX_FICHIER_MO | C6: 1500 | D6: Refus au-delà, avec message explicite à l'utilisateur. | E6: entier
A7: Extraction | B7: TIMEOUT_EXTRACTION_S | C7: 180 | D7: Délai maximal de la phase d'extraction. | E7: entier
A8: Extraction | B8: LIRE_DONNEES | C8: VRAI | D8: Autoriser la lecture des données (nécessaire pour GEN-05 et PQ-08). | E8: VRAI | FAUX
A9: Extraction | B9: ECHANTILLON_LIGNES | C9: 10000 | D9: Taille d'échantillon pour l'inférence de types. | E9: entier
A10: Contexte | B10: DATASET_PARTAGE | C10: FAUX | D10: Si VRAI, désactive la détection d'objets orphelins (DAX-01a, GEN-01). | E10: VRAI | FAUX
A11: Contexte | B11: TYPE_LIVRABLE | C11: Power BI | D11: Pilote la précondition de MOD-07a. | E11: Power BI | App BI | Build
A12: Contexte | B12: TEMPLATE_CDS_UTILISE | C12: VRAI | D12: Si FAUX, DSG-01 et DSG-09 passent en Non applicable. | E12: VRAI | FAUX
A13: Seuils globaux | B13: SEUIL_GROS_MODELE_MO | C13: 1024 | D13: Déclenche la catégorie « Modèle de données conséquent ». | E13: entier
A14: Seuils globaux | B14: SEUIL_LIGNES | C14: 1000000 | D14: Définition d'une table volumineuse. | E14: entier
A15: Décision | B15: TAU_OK_P2 | C15: 0.95 | D15: Seuil OK du profil standard. | E15: 0 à 1
A16: Décision | B16: TAU_PARTIEL_P2 | C16: 0.6 | D16: Seuil PARTIEL du profil standard. | E16: 0 à 1
A17: Décision | B17: TAU_OK_P3 | C17: 0.85 | D17: Seuil OK du profil souple. | E17: 0 à 1
A18: Décision | B18: TAU_PARTIEL_P3 | C18: 0.5 | D18: Seuil PARTIEL du profil souple. | E18: 0 à 1
A19: Décision | B19: CONFIANCE_MIN_AUTOREMPLISSAGE | C19: 0.85 | D19: En dessous, le statut est proposé mais marqué « à confirmer ». | E19: 0 à 1
A20: Décision | B20: CONFIANCE_MIN_KO | C20: 0.8 | D20: En dessous, l'agent ne propose jamais KO (plafond PARTIEL). | E20: 0 à 1
A21: Nommage | B21: LONGUEUR_MAX_NOM | C21: 40 | D21: MOD-05a — concision. | E21: entier
A22: Nommage | B22: ABBR_LIST | C22: Nb;Qte;Mt;Lib;Cd;Ref;Dt;Cli;Frs;Prd;Tot;Dsg;Ct | D22: MOD-05b — abréviations interdites. | E22: liste ;
A23: Nommage | B23: SIGLES_AUTORISES | C23: CA;EBITDA;KPI;TVA;ETP;HT;TTC;BI;RH;QSE;CDS | D23: MOD-05b — liste blanche. | E23: liste ;
A24: Nommage | B24: PREFIXES | C24: D_;F_;T_ | D24: MOD-05c — préfixes attendus. | E24: liste ;
A25: DAX | B25: SEUIL_COMPLEXITE_K | C25: 60 | D25: DAX-03 / DAX-04 — seuil de complexité d'une mesure. | E25: entier
A26: DAX | B26: SEUIL_LONGUEUR_FORMAT | C26: 60 | D26: DAX-02 — longueur au-delà de laquelle un saut de ligne est exigé. | E26: entier
A27: DAX | B27: LARGEUR_MAX_LIGNE | C27: 120 | D27: DAX-02 — largeur maximale d'une ligne. | E27: entier
A28: DAX | B28: SEUIL_DISTANCE_FORMAT | C28: 0.15 | D28: DAX-02 — distance maximale au formatage canonique. | E28: 0 à 1
A29: DAX | B29: TAILLE_MIN_FRAGMENT | C29: 8 | D29: DAX-01b — taille minimale d'un fragment dupliqué (en jetons). | E29: entier
A30: DAX | B30: NB_MIN_OCCURRENCES | C30: 3 | D30: DAX-01b — nb de mesures partageant le fragment. | E30: entier
A31: DAX | B31: SEUIL_SIMILARITE_DOUBLON | C31: 0.85 | D31: DAX-01a — Jaccard minimal pour un quasi-doublon. | E31: 0 à 1
A32: DAX | B32: NB_MIN_VARIANTES_CG | C32: 3 | D32: DAX-05 — taille minimale d'une famille de mesures. | E32: entier
A33: DAX | B33: NB_MIN_ECONOMIE_CG | C33: 8 | D33: DAX-05 — potentiel déclenchant la recommandation. | E33: entier
A34: Power Query | B34: SEUIL_ETAPES_COMMENTAIRE | C34: 12 | D34: DAX-04 — nb d'étapes rendant une requête « complexe ». | E34: entier
A35: Power Query | B35: LONGUEUR_ETAPE_COMPLEXE | C35: 120 | D35: PQ-07 — longueur d'expression rendant une étape non simple. | E35: entier
A36: Power Query | B36: NB_MAX_COUTEUSES | C36: 3 | D36: BIG-02 — nb maximal d'étapes coûteuses par requête. | E36: entier
A37: Power Query | B37: ENDPOINTS_DEDIES | C37: (à renseigner par l'équipe Data) | D37: PQ-05 — liste blanche des HTTP_Path autorisés. | E37: liste ;
A38: Modèle | B38: LONGUEUR_MIN_DESC | C38: 20 | D38: MOD-07 — longueur minimale d'une description. | E38: entier
A39: Modèle | B39: LONGUEUR_MIN_DESC_BUILD | C39: 60 | D39: MOD-07a — longueur minimale sur périmètre Build. | E39: entier
A40: Modèle | B40: SEUIL_MESURES_DOSSIER | C40: 10 | D40: MOD-06b — activation de la règle des dossiers. | E40: entier
A41: Modèle | B41: NB_MAX_TABLES_MESURES | C41: 5 | D41: MOD-06a — éviter l'éparpillement. | E41: entier
A42: Design | B42: SEUIL_VISUELS_GROUPE | C42: 8 | D42: DSG-03 — nb de visuels au-delà duquel le groupement est exigé. | E42: entier
A43: Design | B43: SEUIL_SLICERS_APPLIQUER | C43: 4 | D43: BIG-06 — nb de slicers déclenchant le besoin d'un bouton Appliquer. | E43: entier
A44: Design | B44: MOTIF_BANDEAU | C44: (?i)(derni[eè]re actualisation|donn[ée]es? actualis|notification) | D44: DSG-09 — motif de reconnaissance du bandeau. | E44: regex
A45: Design | B45: TOLERANCE_POSITION_PX | C45: 5 | D45: DSG-01 / DSG-09 — tolérance de positionnement. | E45: entier

Sheet Synthese_Couverture
A1: Couverture de l'automatisation
A2: Calculé par formules sur l'onglet Algorithmes_Regles. Se met à jour si le référentiel évolue.
A4: Catégorie | B4: Points de contrôle | C4: A — Déterministe | D4: B — Heuristique | E4: C — Humaine | F4: Taux d'automatisation
A5: Power Query | B5: =COUNTIFS(Algorithmes_Regles!$B$3:$B$68,$A5,Algorithmes_Regles!$C$3:$C$68,"<>Précondition") -> 14 | C5: =COUNTIFS(Algorithmes_Regles!$B$3:$B$68,$A5,Algorithmes_Regles!$G$3:$G$68,"A",Algorithmes_Regles!$C$3:$C$68,"<>Précondition") -> 10 | D5: =COUNTIFS(Algorithmes_Regles!$B$3:$B$68,$A5,Algorithmes_Regles!$G$3:$G$68,"B",Algorithmes_Regles!$C$3:$C$68,"<>Précondition") -> 4 | E5: =COUNTIFS(Algorithmes_Regles!$B$3:$B$68,$A5,Algorithmes_Regles!$G$3:$G$68,"C",Algorithmes_Regles!$C$3:$C$68,"<>Précondition") -> 0 | F5: =IFERROR(($C5+$D5)/$B5,0) -> 1
A6: Modèle | B6: =COUNTIFS(Algorithmes_Regles!$B$3:$B$68,$A6,Algorithmes_Regles!$C$3:$C$68,"<>Précondition") -> 16 | C6: =COUNTIFS(Algorithmes_Regles!$B$3:$B$68,$A6,Algorithmes_Regles!$G$3:$G$68,"A",Algorithmes_Regles!$C$3:$C$68,"<>Précondition") -> 12 | D6: =COUNTIFS(Algorithmes_Regles!$B$3:$B$68,$A6,Algorithmes_Regles!$G$3:$G$68,"B",Algorithmes_Regles!$C$3:$C$68,"<>Précondition") -> 4 | E6: =COUNTIFS(Algorithmes_Regles!$B$3:$B$68,$A6,Algorithmes_Regles!$G$3:$G$68,"C",Algorithmes_Regles!$C$3:$C$68,"<>Précondition") -> 0 | F6: =IFERROR(($C6+$D6)/$B6,0) -> 1
A7: DAX | B7: =COUNTIFS(Algorithmes_Regles!$B$3:$B$68,$A7,Algorithmes_Regles!$C$3:$C$68,"<>Précondition") -> 8 | C7: =COUNTIFS(Algorithmes_Regles!$B$3:$B$68,$A7,Algorithmes_Regles!$G$3:$G$68,"A",Algorithmes_Regles!$C$3:$C$68,"<>Précondition") -> 4 | D7: =COUNTIFS(Algorithmes_Regles!$B$3:$B$68,$A7,Algorithmes_Regles!$G$3:$G$68,"B",Algorithmes_Regles!$C$3:$C$68,"<>Précondition") -> 4 | E7: =COUNTIFS(Algorithmes_Regles!$B$3:$B$68,$A7,Algorithmes_Regles!$G$3:$G$68,"C",Algorithmes_Regles!$C$3:$C$68,"<>Précondition") -> 0 | F7: =IFERROR(($C7+$D7)/$B7,0) -> 1
A8: Général | B8: =COUNTIFS(Algorithmes_Regles!$B$3:$B$68,$A8,Algorithmes_Regles!$C$3:$C$68,"<>Précondition") -> 5 | C8: =COUNTIFS(Algorithmes_Regles!$B$3:$B$68,$A8,Algorithmes_Regles!$G$3:$G$68,"A",Algorithmes_Regles!$C$3:$C$68,"<>Précondition") -> 3 | D8: =COUNTIFS(Algorithmes_Regles!$B$3:$B$68,$A8,Algorithmes_Regles!$G$3:$G$68,"B",Algorithmes_Regles!$C$3:$C$68,"<>Précondition") -> 1 | E8: =COUNTIFS(Algorithmes_Regles!$B$3:$B$68,$A8,Algorithmes_Regles!$G$3:$G$68,"C",Algorithmes_Regles!$C$3:$C$68,"<>Précondition") -> 1 | F8: =IFERROR(($C8+$D8)/$B8,0) -> 0.8
A9: Mise en page & Design | B9: =COUNTIFS(Algorithmes_Regles!$B$3:$B$68,$A9,Algorithmes_Regles!$C$3:$C$68,"<>Précondition") -> 10 | C9: =COUNTIFS(Algorithmes_Regles!$B$3:$B$68,$A9,Algorithmes_Regles!$G$3:$G$68,"A",Algorithmes_Regles!$C$3:$C$68,"<>Précondition") -> 6 | D9: =COUNTIFS(Algorithmes_Regles!$B$3:$B$68,$A9,Algorithmes_Regles!$G$3:$G$68,"B",Algorithmes_Regles!$C$3:$C$68,"<>Précondition") -> 3 | E9: =COUNTIFS(Algorithmes_Regles!$B$3:$B$68,$A9,Algorithmes_Regles!$G$3:$G$68,"C",Algorithmes_Regles!$C$3:$C$68,"<>Précondition") -> 1 | F9: =IFERROR(($C9+$D9)/$B9,0) -> 0.9
A10: Modèle de données conséquent (> 1Go) | B10: =COUNTIFS(Algorithmes_Regles!$B$3:$B$68,$A10,Algorithmes_Regles!$C$3:$C$68,"<>Précondition") -> 6 | C10: =COUNTIFS(Algorithmes_Regles!$B$3:$B$68,$A10,Algorithmes_Regles!$G$3:$G$68,"A",Algorithmes_Regles!$C$3:$C$68,"<>Précondition") -> 4 | D10: =COUNTIFS(Algorithmes_Regles!$B$3:$B$68,$A10,Algorithmes_Regles!$G$3:$G$68,"B",Algorithmes_Regles!$C$3:$C$68,"<>Précondition") -> 1 | E10: =COUNTIFS(Algorithmes_Regles!$B$3:$B$68,$A10,Algorithmes_Regles!$G$3:$G$68,"C",Algorithmes_Regles!$C$3:$C$68,"<>Précondition") -> 1 | F10: =IFERROR(($C10+$D10)/$B10,0) -> 0.83333333
A11: TOTAL | B11: =SUM(B5:B10) -> 59 | C11: =SUM(C5:C10) -> 39 | D11: =SUM(D5:D10) -> 17 | E11: =SUM(E5:E10) -> 3 | F11: =IFERROR(($C11+$D11)/$B11,0) -> 0.94915254
A13: Répartition par criticité
A14: Criticité | B14: Points de contrôle | C14: Dont automatisables (A+B) | D14: Taux
A15: Bloquant | B15: =COUNTIF(Algorithmes_Regles!$F$3:$F$68,$A15) -> 12 | C15: =COUNTIFS(Algorithmes_Regles!$F$3:$F$68,$A15,Algorithmes_Regles!$G$3:$G$68,"A")+COUNTIFS(Algorithmes_Regles!$F$3:$F$68,$A15,Algorithmes_Regles!$G$3:$G$68,"B") -> 12 | D15: =IFERROR($C15/$B15,0) -> 1
A16: Recommandé | B16: =COUNTIF(Algorithmes_Regles!$F$3:$F$68,$A16) -> 46 | C16: =COUNTIFS(Algorithmes_Regles!$F$3:$F$68,$A16,Algorithmes_Regles!$G$3:$G$68,"A")+COUNTIFS(Algorithmes_Regles!$F$3:$F$68,$A16,Algorithmes_Regles!$G$3:$G$68,"B") -> 43 | D16: =IFERROR($C16/$B16,0) -> 0.93478261
A17: Optionnel | B17: =COUNTIF(Algorithmes_Regles!$F$3:$F$68,$A17) -> 1 | C17: =COUNTIFS(Algorithmes_Regles!$F$3:$F$68,$A17,Algorithmes_Regles!$G$3:$G$68,"A")+COUNTIFS(Algorithmes_Regles!$F$3:$F$68,$A17,Algorithmes_Regles!$G$3:$G$68,"B") -> 1 | D17: =IFERROR($C17/$B17,0) -> 1
A19: Lecture : le taux d'automatisation additionne les classes A et B, c'est-à-dire les points de contrôle pour lesquels l'agent propose un statut. Les points de classe C restent NON RENSEIGNÉS et sont accompagnés d'un pré-diagnostic chiffré destiné au relecteur.

Sheet Schema_MIR
A1: Représentation intermédiaire normalisée (MIR)
A2: Toutes les règles s'exécutent sur cette structure, jamais sur le fichier d'origine. C'est elle qui rend l'agent indépendant du format d'entrée (pbip, pbix ou XMLA) et qui garantit qu'un même rapport donne le même score quelle que soit la source.
A5: Entité MIR | B5: Attributs normalisés | C5: Nature | D5: Source d'extraction | E5: Règles consommatrices
A6: model | B6: name, culture, compatibilityLevel, discourageImplicitMeasures, annotations{}, tailleMo | C6: Modèle sémantique | D6: TMDL / model.bim / XMLA | E6: GEN-02, MOD-02, BIG-00
A7: tables[] | B7: name, isHidden, dataCategory, description, classe(FAIT|DIM|TECH), nbLignes, tailleMo, refreshPolicy | C7: Tables | D7: TMDL / model.bim | E7: MOD-01, MOD-03a, MOD-05c, BIG-04
A8: columns[] | B8: table, name, dataType, formatString, summarizeBy, isHidden, isKey, sortByColumn, displayFolder, description, distinctCount, tailleMo, sourceExpression | C8: Colonnes | D8: TMDL + stats VertiPaq | E8: PQ-02, PQ-08, MOD-02, MOD-03, MOD-07
A9: measures[] | B9: table, name, expression, formatString, displayFolder, description, isHidden, tokens[], ast, K(complexité), hash, dependances[] | C9: Mesures | D9: TMDL + analyseur DAX | E9: DAX-01→06, MOD-06, MOD-07
A10: relationships[] | B10: from(table,col), to(table,col), fromCardinality, toCardinality, crossFilteringBehavior, isActive, relyOnReferentialIntegrity | C10: Relations | D10: TMDL / model.bim | E10: MOD-04, GEN-05
A11: partitions[] | B11: table, name, mode(import|directQuery|dual), sourceType, expressionRef | C11: Partitions | D11: TMDL / model.bim | E11: PQ-05, BIG-06
A12: mQueries[] | B12: name, isParameter, isFunction, loadEnabled, steps[](name, function, expression, foldable, position), connecteur, args{}, dependances[] | C12: Code Power Query | D12: DataMashup / Section1.m | E12: PQ-01→07, BIG-01→04
A13: parameters[] | B13: name, type, defaultValue, description, usages[] | C13: Paramètres M | D13: Section1.m | E13: PQ-03, PQ-06, BIG-03
A14: pages[] | B14: name, displayName, ordinal, width, height, displayOption, visibility, type(normal|tooltip|drillthrough), mobileLayout | C14: Pages du rapport | D14: Layout / report.json | E14: DSG-02, DSG-10
A15: visuals[] | B15: page, id, name, type, x, y, w, h, isHidden, parentGroup, projections[](queryRef, aggregation), filters[], objects{}, signature | C15: Visuels | D15: Layout / report.json | E15: DSG-03→08, DAX-01
A16: interactions[] | B16: page, source, cible, type(none|filter|highlight), explicite | C16: Matrice d'interactions | D16: Layout (relationships) | E16: DSG-04, DSG-05
... A21: fingerprint | B21: Merkle : hash par table / requête / page, puis racine | C21: Empreinte du modèle | D21: Calculé | E21: Cache et ré-analyse incrémentale

Sheet Questions_Ouvertes
A1: Décisions à arbitrer avant développement
A2: Colonne « Votre réponse » à compléter (cellules jaunes). Sans réponse, l'agent est construit avec la valeur par défaut proposée.
A4: N° | B4: Thème | C4: Question | D4: Proposition par défaut | E4: Votre réponse
A5: Q1 | B5: Entrée | C5: Quel format d'entrée retient-on en priorité ? Le format PBIP (dossier de projet Power BI, contenu 100 % texte) rend l'analyse déterministe, complète et exécutable sur Linux. Le .pbix impose de décompresser un flux propriétaire pour atteindre le modèle sémantique. | D5: PBIP en priorité, .pbix accepté en dégradé (rapport + Power Query complets, modèle sémantique partiel).
A6: Q2 | B6: Entrée | C6: Les rapports à auditer sont-ils publiés sur un espace de travail Premium / Fabric avec point de terminaison XMLA activé ? | D6: Si oui, ajouter un troisième mode de collecte par XMLA en lecture seule : c'est le plus fiable et il évite tout téléversement de fichier.
A7: Q3 | B7: Données | C7: L'agent est-il autorisé à lire les DONNÉES contenues dans le modèle, et pas seulement sa structure ? Deux règles en dépendent : l'intégrité référentielle (GEN-05) et la cardinalité (PQ-08). | D7: Oui, lecture en mémoire uniquement, aucune donnée persistée, suppression du fichier après analyse selon la rétention déjà paramétrée dans Veridash.
A8: Q4 | B8: Statuts | C8: L'agent doit-il pouvoir proposer le statut PARTIEL, ou se limiter à OK / KO / NA ? | D8: Conserver PARTIEL : la formule de score de Veridash le valorise à 0,5 et il évite de sanctionner un modèle conforme à 90 %.
A9: Q5 | B9: Statuts | C9: Quand la confiance est faible, préfère-t-on un statut proposé et signalé « à confirmer », ou un point laissé vide ? | D9: Statut proposé et signalé, sauf en classe C où le point reste vide avec un pré-diagnostic.
A10: Q6 | B10: Statuts | C10: Que fait l'agent sur un point déjà renseigné par un humain lors d'une seconde exécution ? | D10: Il ne l'écrase jamais. Il produit un écart signalé, visible dans le rapport d'analyse.
A11: Q7 | B11: Périmètre | C11: Les sous-règles (les lignes commençant par « -> ») doivent-elles compter dans le score au même titre que les règles mères, ou seulement alimenter le verdict de la mère ? | D11: Seules les règles mères comptent dans le score ; les sous-règles servent de justification et de plan d'action. À confirmer car cela change le dénominateur.
A12: Q8 | B12: Seuils | C12: Valide-t-on les profils de seuils proposés (P1 strict à 100 %, P2 standard à 95 %/60 %, P3 souple à 85 %/50 %) ? | D12: Oui, avec calibrage sur 5 à 10 rapports déjà audités manuellement avant mise en service.
A13: Q9 | B13: Référentiels | C13: Qui fournit la liste blanche des points de terminaison Databricks dédiés (PQ-05) et le fichier de thème CDS de référence (DSG-01, DSG-09) ? | D13: Sans ces deux référentiels, 3 règles restent en Non applicable. À charger une fois pour toutes dans l'administration Veridash.
A14: Q10 | B14: Référentiels | C14: Quels sigles métier Colas doivent figurer en liste blanche pour la détection d'abréviations (MOD-05b) ? | D14: Liste initiale proposée dans l'onglet Parametres, à compléter.
A15: Q11 | B15: Langue | C15: Les rapports sont-ils développés avec Power BI Desktop en français, en anglais, ou les deux ? | D15: Les deux : le dictionnaire de noms d'étapes automatiques (PQ-07) doit couvrir FR et EN.
A16: Q12 | B16: IA | C16: Autorise-t-on un second passage par un modèle de langage pour les règles subjectives (qualité des commentaires, cohérence des noms, pertinence des descriptions) ? | D16: Optionnel, désactivé par défaut. Si activé, il n'intervient qu'en complément d'un verdict déjà calculé et ne peut que faire passer de KO à PARTIEL, jamais l'inverse.
... A20: Q16 | B20: Interface | C20: Le bouton « Utiliser l'agent BI » doit-il proposer un mode simulation (analyse et aperçu du remplissage sans écriture) avant application ? | D20: Oui : aperçu systématique, application sur confirmation explicite, annulation possible en un geste.
